Q5_FlipFlops/q5_RSff_design.v
`timescale 1ns/1ns

// Reset is active high
module RS_flipflop(input R, S, input clk, input reset, output reg q, qbar);
    always @(posedge clk or posedge reset)
    begin
        if (reset) begin
            q <= 1'b0;
            qbar <= 1'b1;
        end
        else begin
            if (R & ~S) begin
                q <= 1'b0;
                qbar <= 1'b1;
            end
            else if (~R & S) begin
                q <= 1'b1;
                qbar <= 1'b0;
            end
            else if (R & S) begin
                q <= 1'b1;
                qbar <= 1'b1;
            end
        end
    end
endmodule

Q5_FlipFlops/q5_RSff_tb.v
`timescale 1ns/1ns
`include "q5_RSff_design.v"

module RS_flipflop_test();
    reg R, S, clk, reset;
    wire q, qbar;
    RS_flipflop uut(
        .R(R),
        .S(S),
        .clk(clk),
        .reset(reset),
        .q(q),
        .qbar(qbar)
    );

    initial begin
        $dumpfile("q5_RSff.vcd");
        $dumpvars(0, RS_flipflop_test);
        for (integer i = 0;i< 2;i = i+1)
        begin
            for (integer j = 0;j< 2;j = j+1)
            begin
                for (integer k = 0;k< 2;k = k+1)
                begin
                    R = i;
                    S = j;
                    clk = k;
                    reset = 0;
                    #10;
                end
            end
        end
        $finish;
    end

    initial begin
        $monitor("Time = %0t: R = %b, S = %b, clk = %b, reset = %b, q = %b, qbar = %b",
         $time, R, S, clk, reset, q, qbar);
    end
endmodule

Q5_FlipFlops/q5_RSff.vcd
$date
	Fri Oct  4 19:10:43 2024
$end
$version
	Icarus Verilog
$end
$timescale
	1ns
$end
$scope module RS_flipflop_test $end
$var wire 1 ! qbar $end
$var wire 1 " q $end
$var reg 1 # R $end
$var reg 1 $ S $end
$var reg 1 % clk $end
$var reg 1 & reset $end
$scope module uut $end
$var wire 1 # R $end
$var wire 1 $ S $end
$var wire 1 % clk $end
$var wire 1 & reset $end
$var reg 1 " q $end
$var reg 1 ! qbar $end
$upscope $end
$scope begin $ivl_for_loop0 $end
$var integer 32 ' i [31:0] $end
$scope begin $ivl_for_loop1 $end
$var integer 32 ( j [31:0] $end
$scope begin $ivl_for_loop2 $end
$var integer 32 ) k [31:0] $end
$upscope $end
$upscope $end
$upscope $end
$upscope $end
$enddefinitions $end
#0
$dumpvars
b0 )
b0 (
b0 '
0&
0%
0$
0#
x"
x!
$end
#10
1%
b1 )
#20
0%
1$
b1 (
b0 )
#30
0!
1"
1%
b1 )
#40
0%
0$
1#
b1 '
b0 (
b0 )
#50
1!
0"
1%
b1 )
#60
0%
1$
b1 (
b0 )
#70
1"
1%
b1 )
#80
b10 '
b10 (
b10 )
