Q3_Mux_Demux_Decoders/Demux/q3_demux_design.v
`timescale 1ns/1ns

module demux_1x2(input I, input S, output A, output B);
    assign A = (~S) & I;
    assign B = S & I;
endmodule

module demux_1x4(input I, input [1:0] S, output A, output B, output C, output D);
    demux_1x2 demux_1x2_1(.I(I), .S(S[1]), .A(temp1), .B(temp2));
    demux_1x2 demux_1x2_2(.I(temp1), .S(S[0]), .A(A), .B(B));
    demux_1x2 demux_1x2_3(.I(temp2), .S(S[0]), .A(C), .B(D));
endmodule

module demux_1x8(input I, input [2:0] S, output A, output B, output C, output D, output E, output F, output G, output H);
    demux_1x2 demux_1x2_1(.I(I), .S(S[2]), .A(temp1), .B(temp2));
    demux_1x4 demux_1x4_1(.I(temp1), .S(S[1:0]), .A(A), .B(B), .C(C), .D(D));
    demux_1x4 demux_1x4_2(.I(temp2), .S(S[1:0]), .A(E), .B(F), .C(G), .D(H));
endmodule

Q3_Mux_Demux_Decoders/Demux/q3_demux_tb.v
`timescale 1ns/1ns

`include "q3_demux_design.v"

// module demux_1x2_test;
//     reg I, S;

//     demux_1x2 uut(
//         .I(I),
//         .S(S),
//         .A(A),
//         .B(B)
//     );

//     initial begin
//         $dumpfile("q3_demux.vcd");
//         $dumpvars(0, demux_1x2_test);

//         for (integer i = 0;i< 2;i = i+1)
//         begin
//             I = 1; S = i;
//             #10;              
//         end
//         $finish;
//     end

//     initial begin
//         $monitor("Time = %0t: I = %b, S = %b, A = %b, B = %b", 
//         $time, I, S, A, B);
//     end
// endmodule

// module demux_1x4_test;
//     reg I;
//     reg [1:0] S;

//     demux_1x4 uut(
//         .I(I),
//         .S(S),
//         .A(A),
//         .B(B),
//         .C(C),
//         .D(D)
//     );

//     initial begin
//         $dumpfile("q3_demux.vcd");
//         $dumpvars(0, demux_1x4_test);

//         for (integer i = 0;i< 4;i = i+1)
//         begin
//             I = 1; S = i;
//             #10; 
//         end
//         $finish;
//     end

//     initial begin
//         $monitor("Time = %0t: I = %b, S = %b, A = %b, B = %b, C = %b, D = %b", 
//         $time, I, S, A, B, C, D);
//     end
// endmodule

module demux_1x8_test;
    reg I;
    reg [2:0] S;

    demux_1x8 uut(
        .I(I),
        .S(S),
        .A(A),
        .B(B),
        .C(C),
        .D(D),
        .E(E),
        .F(F),
        .G(G),
        .H(H)
    );

    initial begin
        $dumpfile("q3_demux.vcd");
        $dumpvars(0, demux_1x8_test);

        for (integer i = 0;i< 8;i = i+1)
        begin
            I = 1; S = i;
            #10; 
        end
        $finish;
    end

    initial begin
        $monitor("Time = %0t: I = %b, S = %b, A = %b, B = %b, C = %b, D = %b, E = %b, F = %b, G = %b, H = %b", 
        $time, I, S, A, B, C, D, E, F, G, H);
    end
endmodule

Q3_Mux_Demux_Decoders/Demux/q3_demux.vcd
$date
	Wed Oct  2 22:09:45 2024
$end
$version
	Icarus Verilog
$end
$timescale
	1ns
$end
$scope module demux_1x8_test $end
$var wire 1 ! H $end
$var wire 1 " G $end
$var wire 1 # F $end
$var wire 1 $ E $end
$var wire 1 % D $end
$var wire 1 & C $end
$var wire 1 ' B $end
$var wire 1 ( A $end
$var reg 1 ) I $end
$var reg 3 * S [2:0] $end
$scope module uut $end
$var wire 1 ) I $end
$var wire 3 + S [2:0] $end
$var wire 1 , temp2 $end
$var wire 1 - temp1 $end
$var wire 1 ! H $end
$var wire 1 " G $end
$var wire 1 # F $end
$var wire 1 $ E $end
$var wire 1 % D $end
$var wire 1 & C $end
$var wire 1 ' B $end
$var wire 1 ( A $end
$scope module demux_1x2_1 $end
$var wire 1 - A $end
$var wire 1 , B $end
$var wire 1 ) I $end
$var wire 1 . S $end
$upscope $end
$scope module demux_1x4_1 $end
$var wire 1 - I $end
$var wire 2 / S [1:0] $end
$var wire 1 0 temp2 $end
$var wire 1 1 temp1 $end
$var wire 1 % D $end
$var wire 1 & C $end
$var wire 1 ' B $end
$var wire 1 ( A $end
$scope module demux_1x2_1 $end
$var wire 1 1 A $end
$var wire 1 0 B $end
$var wire 1 - I $end
$var wire 1 2 S $end
$upscope $end
$scope module demux_1x2_2 $end
$var wire 1 ( A $end
$var wire 1 ' B $end
$var wire 1 1 I $end
$var wire 1 3 S $end
$upscope $end
$scope module demux_1x2_3 $end
$var wire 1 & A $end
$var wire 1 % B $end
$var wire 1 0 I $end
$var wire 1 4 S $end
$upscope $end
$upscope $end
$scope module demux_1x4_2 $end
$var wire 1 , I $end
$var wire 2 5 S [1:0] $end
$var wire 1 6 temp2 $end
$var wire 1 7 temp1 $end
$var wire 1 ! D $end
$var wire 1 " C $end
$var wire 1 # B $end
$var wire 1 $ A $end
$scope module demux_1x2_1 $end
$var wire 1 7 A $end
$var wire 1 6 B $end
$var wire 1 , I $end
$var wire 1 8 S $end
$upscope $end
$scope module demux_1x2_2 $end
$var wire 1 $ A $end
$var wire 1 # B $end
$var wire 1 7 I $end
$var wire 1 9 S $end
$upscope $end
$scope module demux_1x2_3 $end
$var wire 1 " A $end
$var wire 1 ! B $end
$var wire 1 6 I $end
$var wire 1 : S $end
$upscope $end
$upscope $end
$upscope $end
$scope begin $ivl_for_loop0 $end
$var integer 32 ; i [31:0] $end
$upscope $end
$upscope $end
$enddefinitions $end
#0
$dumpvars
b0 ;
0:
09
08
07
06
b0 5
04
03
02
11
00
b0 /
0.
1-
0,
b0 +
b0 *
1)
1(
0'
0&
0%
0$
0#
0"
0!
$end
#10
0(
1'
13
14
19
1:
b1 /
b1 5
b1 *
b1 +
b1 ;
#20
01
0(
1&
10
0'
12
03
04
18
09
0:
b10 /
b10 5
b10 *
b10 +
b10 ;
#30
0&
1%
13
14
19
1:
b11 /
b11 5
b11 *
b11 +
b11 ;
#40
1$
0-
17
00
0%
1,
02
03
04
08
09
0:
1.
b0 /
b0 5
b100 *
b100 +
b100 ;
#50
0$
1#
13
14
19
1:
b1 /
b1 5
b101 *
b101 +
b101 ;
#60
07
0$
1"
16
0#
12
03
04
18
09
0:
b10 /
b10 5
b110 *
b110 +
b110 ;
#70
0"
1!
13
14
19
1:
b11 /
b11 5
b111 *
b111 +
b111 ;
#80
b1000 ;
