Q10_Finite_State_Machines/q10_moore_fsm_design.v
`timescale 1ns/1ns

// Reset is Active High
module moore_fsm(input clk, reset, input x, output reg y, 
output reg [1:0] state);
    reg [1:0] next_state;

    parameter S_a = 2'b00, S_b = 2'b01, S_c = 2'b10, S_d = 2'b11;
    
    always @(posedge clk or posedge reset)
    begin
        if (reset) begin
            state <= S_a;
            next_state <= S_a;
            y <= 1'b0;
        end
        else begin
            state <= next_state;
            case (state)
                S_a: begin
                    if (x==1)
                        next_state <= S_c;
                    else
                        next_state <= S_b;
                    y <= 1'b0;
                end
                S_b: begin
                    if (x==1)
                        next_state <= S_d;
                    else
                        next_state <= S_c;
                    y <= 1'b1;
                end
                S_c: begin
                    if (x==1)
                        next_state <= S_d;
                    else
                        next_state <= S_b;
                    y <= 1'b1;
                end
                S_d: begin
                    if (x==1)
                        next_state <= S_a;
                    else
                        next_state <= S_c;
                    y <= 1'b0;
                end
            endcase
        end
    end
endmodule

Q10_Finite_State_Machines/q10_moore_fsm_tb.v
`timescale 1ns/1ns
`include "q10_moore_fsm_design.v"

module moore_fsm_tb();    
    reg clk, reset, x;
    wire [1:0] state;
    wire y;

    moore_fsm uut(
        .clk(clk),
        .reset(reset),
        .x(x),
        .state(state),
        .y(y)
    );

    initial begin
        clk = 0;
        forever begin
            #5 clk = ~clk;
        end
    end

    initial begin
        $dumpfile("q10_moore_fsm.vcd");
        $dumpvars(0, moore_fsm_tb);
        
        reset =1;
        x = 0;
        #10
        reset = 0;
        x = 0; #20;
        x = 0; #20;
        x = 1; #20;
        x = 1; #20; // back to state 0
        $display("Back to state a");
        x = 1; #20;
        x = 1; #20;
        x = 1; #20; // back to state 0
        $display("Back to state a");
        x = 0; #20;
        x = 1; #20;
        x = 1; #30;
        $display("Back to state a");
        $finish;
    end

    initial begin
        $monitor("Time = %0t: clk = %b, reset = %b, x = %b, state = %b , y = %b", 
        $time, clk, reset, x, state , y);
    end
endmodule

Q10_Finite_State_Machines/q10_moore_fsm.vcd
$date
	Mon Oct  7 17:20:47 2024
$end
$version
	Icarus Verilog
$end
$timescale
	1ns
$end
$scope module moore_fsm_tb $end
$var wire 1 ! y $end
$var wire 2 " state [1:0] $end
$var reg 1 # clk $end
$var reg 1 $ reset $end
$var reg 1 % x $end
$scope module uut $end
$var wire 1 # clk $end
$var wire 1 $ reset $end
$var wire 1 % x $end
$var reg 2 & next_state [1:0] $end
$var reg 2 ' state [1:0] $end
$var reg 1 ! y $end
$upscope $end
$upscope $end
$enddefinitions $end
#0
$dumpvars
b0 '
b0 &
0%
1$
0#
b0 "
0!
$end
#5
1#
#10
0#
0$
#15
b1 &
1#
#20
0#
#25
b1 "
b1 '
1#
#30
0#
#35
1!
b10 &
1#
#40
0#
#45
b10 "
b10 '
1#
#50
0#
1%
#55
b11 &
1#
#60
0#
#65
b11 "
b11 '
1#
#70
0#
#75
0!
b0 &
1#
#80
0#
#85
b0 "
b0 '
1#
#90
0#
#95
b10 &
1#
#100
0#
#105
b10 "
b10 '
1#
#110
0#
#115
1!
b11 &
1#
#120
0#
#125
b11 "
b11 '
1#
#130
0#
#135
0!
b0 &
1#
#140
0#
#145
b0 "
b0 '
1#
#150
0#
0%
#155
b1 &
1#
#160
0#
#165
b1 "
b1 '
1#
#170
0#
1%
#175
1!
b11 &
1#
#180
0#
#185
b11 "
b11 '
1#
#190
0#
#195
0!
b0 &
1#
#200
0#
#205
b0 "
b0 '
1#
#210
0#
#215
b10 &
1#
