Q11_Two_1_0_detector/q11_design.v
`timescale 1ns/1ns

module q11(input clk, reset, ONE, ZERO, output reg [3:0] state, output out);
    parameter S_0_0 = 0; // 0 ones and 0 zeroes
    parameter S_0_1 = 1; // 0 ones and 1 zeroes
    parameter S_0_2 = 2; // 0 ones and 2 zeroes
    parameter S_1_0 = 3; // 1 ones and 0 zeroes
    parameter S_1_1 = 4; // 1 ones and 1 zeroes
    parameter S_1_2 = 5; // 1 ones and 2 zeroes
    parameter S_2_0 = 6; // 2 ones and 0 zeroes
    parameter S_2_1 = 7; // 2 ones and 1 zeroes
    parameter S_2_2 = 8; // 2 ones and 2 zeroes

    reg prev_one, prev_zero;
    // reg [3:0] state;
    wire in_one, in_zero;

    always @(posedge clk or posedge reset) begin
        prev_one <= reset ? 0 : ONE;
        prev_zero <= reset ? 0 : ZERO;
    end

    assign in_one = ~prev_one & ONE;
    assign in_zero = ~prev_zero & ZERO;

    always@(posedge clk)
    begin
        if(reset)
            state <= S_0_0;
        else
            case(state)
                S_0_0: 
                begin
                    if (in_one)
                        state <= S_1_0;
                    else if (in_zero)
                        state <= S_0_1;
                    else
                        state <= state;
                end
                S_0_1:
                begin
                    if (in_one)
                        state <= S_1_1;
                    else if (in_zero)
                        state <= S_0_2;
                    else
                        state <= state;
                end
                S_0_2:
                begin
                    if (in_one)
                        state <= S_1_2;
                    else
                        state <= state;
                end 
                S_1_0:
                begin
                    if (in_one)
                        state <= S_2_0;
                    else if (in_zero)
                        state <= S_1_1;
                    else
                        state <= state;
                end
                S_1_1:
                begin
                    if (in_one)
                        state <= S_2_1;
                    else if (in_zero)
                        state <= S_1_2;
                    else
                        state <= state;
                end
                S_1_2:
                begin
                    if (in_one)
                        state <= S_2_2;
                    else
                        state <= state;
                end
                S_2_0:
                begin
                    if (in_zero)
                        state <= S_2_1;
                    else
                        state <= state;
                end
                S_2_1:
                begin
                    if (in_zero)
                        state <= S_2_2;
                    else
                        state <= state;
                end
                S_2_2:
                begin
                    state <= state;
                end
                default: state <= S_0_0;
            endcase
    end
    assign out = (state == S_2_2);
endmodule

Q11_Two_1_0_detector/q11_tb.v
`timescale 1ns/1ns
`include "q11_design.v"

module q11_test();
    reg clk, reset, ONE, ZERO;
    wire out;
    wire [3:0] state;

    q11 uut(
        .clk(clk),
        .reset(reset),
        .ONE(ONE),
        .ZERO(ZERO),
        .state(state),
        .out(out)
    );

    initial begin
        clk = 0;
        forever begin
            #5 clk = ~clk;
        end
    end

    initial begin
        $dumpfile("q11.vcd");
        $dumpvars(0, q11_test);
        
        reset =1;
        ONE = 0;
        ZERO = 0;
        #10
        reset = 0;
        ONE = 1; ZERO = 0; #10;
        ONE = 0; ZERO = 1; #10; // back to state 0
        ONE = 1; ZERO = 0; #10;
        ONE = 0; ZERO = 1; #10;
        $finish;
    end

    initial begin
        $monitor("Time = %0t: clk = %b, reset = %b, ONE = %b, ZERO = %b, State = %b, out = %b", $time, clk, reset, ONE, ZERO, state, out);
    end
endmodule

Q11_Two_1_0_detector/q11.vcd
$date
	Sun Oct  6 16:33:35 2024
$end
$version
	Icarus Verilog
$end
$timescale
	1ns
$end
$scope module q11_test $end
$var wire 4 ! state [3:0] $end
$var wire 1 " out $end
$var reg 1 # ONE $end
$var reg 1 $ ZERO $end
$var reg 1 % clk $end
$var reg 1 & reset $end
$scope module uut $end
$var wire 1 # ONE $end
$var wire 1 $ ZERO $end
$var wire 1 % clk $end
$var wire 1 ' in_one $end
$var wire 1 ( in_zero $end
$var wire 1 & reset $end
$var wire 1 " out $end
$var reg 1 ) prev_one $end
$var reg 1 * prev_zero $end
$var reg 4 + state [3:0] $end
$upscope $end
$upscope $end
$enddefinitions $end
#0
$dumpvars
bx +
0*
0)
0(
0'
1&
0%
0$
0#
x"
bx !
$end
#5
0"
b0 !
b0 +
1%
#10
1'
0%
1#
0&
#15
0'
b11 !
b11 +
1)
1%
#20
1(
0%
1$
0#
#25
0(
b100 !
b100 +
1*
0)
1%
#30
1'
0%
0$
1#
#35
0'
b111 !
b111 +
0*
1)
1%
#40
1(
0%
1$
0#
#45
0(
1"
b1000 !
b1000 +
1*
0)
1%
