Q9_Sequential_Circuits/q9b_design.v
`timescale 1ns/1ns

// Reset is Active High
module q9b(input clk, input reset, output reg A, B);
    always @(posedge clk or posedge reset)
    begin
        if (reset) begin
            A <= 1'b0;
            B <= 1'b0;
        end
        else begin
            if ((~A) & (~B)) begin
                A <= 1'b0;
                B <= 1'b1;                
            end
            else if ((~A) & B) begin
                A <= 1'b1;
                B <= 1'b0;
            end
            else if (A & (~B)) begin
                A <= 1'b0;
                B <= 1'b0;
            end
            else if (A & B) begin
                A <= 1'b0;
                B <= 1'b0;
            end
        end
    end
endmodule

Q9_Sequential_Circuits/q9b_tb.v
`timescale 1ns/1ns
`include "q9b_design.v"

module q9b_test();
    reg clk, reset;
    wire A, B;

    q9b uut(clk, reset, A, B);

    initial begin
        clk = 0;
        forever begin
            #5 clk = ~clk;
        end
    end

    initial begin
        $dumpfile("q9b.vcd");
        $dumpvars(0, q9b_test);
        reset =1;
        #10;
        reset = 0;

        for (integer i = 0;i< 6;i = i+1)
        begin
            #10;
        end
        $finish;
    end

    initial begin
        $monitor("Time = %0t: clk = %b, reset = %b, A = %b, B = %b", 
        $time, clk, reset, A, B);
    end

endmodule

Q9_Sequential_Circuits/q9b.vcd
$date
	Sun Oct  6 22:42:19 2024
$end
$version
	Icarus Verilog
$end
$timescale
	1ns
$end
$scope module q9b_test $end
$var wire 1 ! B $end
$var wire 1 " A $end
$var reg 1 # clk $end
$var reg 1 $ reset $end
$scope module uut $end
$var wire 1 # clk $end
$var wire 1 $ reset $end
$var reg 1 " A $end
$var reg 1 ! B $end
$upscope $end
$scope begin $ivl_for_loop0 $end
$var integer 32 % i [31:0] $end
$upscope $end
$upscope $end
$enddefinitions $end
#0
$dumpvars
bx %
1$
0#
0"
0!
$end
#5
1#
#10
0#
b0 %
0$
#15
1!
1#
#20
0#
b1 %
#25
0!
1"
1#
#30
0#
b10 %
#35
0"
1#
#40
0#
b11 %
#45
1!
1#
#50
0#
b100 %
#55
0!
1"
1#
#60
0#
b101 %
#65
0"
1#
#70
0#
b110 %
