Q4_Adders/q4_cla_design.v
`timescale 1ns/1ns

module four_bit_cla(input [3:0] A, B, input C0, output [3:0] S, output Cout);
    wire [4:0] C;

    // Propagate and Generate Block
    xor(P0, A[0], B[0]);
    xor(P1, A[1], B[1]);
    xor(P2, A[2], B[2]);
    xor(P3, A[3], B[3]);

    and(G0, A[0], B[0]);
    and(G1, A[1], B[1]);
    and(G2, A[2], B[2]);
    and(G3, A[3], B[3]);

    // Carry Lookahead Block
    // C[1] = G0 + P0*C0
    and(x1, P0, C0);
    
    // C[2] = G1 + P1*G0 + P1*P0*C0
    and(x2, P1, G0);
    and(x3, P1, P0, C0);
    
    // C[3] = G2 + P2*G1 + P2*P1*G0 + P2*P1*P0*C0
    and(x4, P2, G1);
    and(x5, P2, P1, G0);
    and(x6, P2, P1, P0, C0);
    
    // C[4] = G3 + P3*G2 + P3*P2*G1 + P3*P2*P1*G0 + P3*P2*P1*P0*C0
    and(x7, P3, G2);
    and(x8, P3, P2, G1);
    and(x9, P3, P2, P1, G0);
    and(x10, P3, P2, P1, P0, C0);  
    
    assign C[0] = C0; 
    or(C[1], G0, x1);
    or(C[2], G1, x2, x3);
    or(C[3], G2, x4, x5, x6);
    or(C[4], G3, x7, x8, x9, x10);
    
    // Sum Block
    xor(S[0], P0, C[0]);
    xor(S[1], P1, C[1]);
    xor(S[2], P2, C[2]);
    xor(S[3], P3, C[3]);

    assign Cout = C[4];
endmodule

// use 4 bit cla to design 16 bit cla
module sixteen_bit_cla(input [15:0] A, B, input C0, output [15:0] S, output Cout);
    wire [3:0] C;

    four_bit_cla uut0(
        .A(A[3:0]),
        .B(B[3:0]),
        .C0(C0),
        .S(S[3:0]),
        .Cout(C[0])
    );

    four_bit_cla uut1(
        .A(A[7:4]),
        .B(B[7:4]),
        .C0(C[0]),
        .S(S[7:4]),
        .Cout(C[1])
    );

    four_bit_cla uut2(
        .A(A[11:8]),
        .B(B[11:8]),
        .C0(C[1]),
        .S(S[11:8]),
        .Cout(C[2])
    );

    four_bit_cla uut3(
        .A(A[15:12]),
        .B(B[15:12]),
        .C0(C[2]),
        .S(S[15:12]),
        .Cout(C[3])
    );

    assign Cout = C[3];
endmodule

Q4_Adders/q4_cla_tb.v
`timescale 1ns/1ns
`include "q4_cla_design.v"

module four_bit_cla_test();
    reg [3:0] A, B; 
    reg C0;
    wire [3:0] S; 
    wire Cout;
    four_bit_cla uut(
        .A(A),
        .B(B),
        .C0(C0),
        .S(S),
        .Cout(Cout)
    );

    initial begin
        $dumpfile("q4_cla.vcd");
        $dumpvars(0, four_bit_cla_test);
        for (integer i = 0;i< 16;i = i+1)
        begin
            for (integer j = 0;j< 16;j = j+1)
            begin
                for (integer k = 0;k< 2;k = k+1)
                begin
                    A = i;
                    B = j;
                    C0 = k;
                    #10;
                end
            end
        end
        $finish;
    end

    initial begin
        $monitor("Time = %0t: A = %b, B = %b, C0 = %b,Cout = %b, S = %b", $time, A, B, C0, Cout, S);
    end
endmodule

// module sixteen_bit_cla_test();
//     reg [15:0] A, B; 
//     reg C0;
//     wire [15:0] S; 
//     wire Cout;
//     sixteen_bit_cla uut(
//         .A(A),
//         .B(B),
//         .C0(C0),
//         .S(S),
//         .Cout(Cout)
//     );

//     initial begin
//         $dumpfile("q4_cla.vcd");
//         $dumpvars(0, sixteen_bit_cla_test);
    
//         $display("Testcase -1");
//         A = 23541;
//         B = 12352;
//         C0 = 1;
//         $display("A = %d, B = %d, C = %d", A, B, C0);
//         #10;
//         $display("Expected Answer = %d", A + B + C0);
//         $display("Answer calculated = %d\n", S);
//         C0 = 0;
//         #10;
        
//         $display("Testcase -2");
//         A = 12343;
//         B = 12368;
//         C0 = 0;
//         $display("A = %d, B = %d, C = %d", A, B, C0);
//         #10;
//         $display("Expected Answer = %d", A + B + C0);
//         $display("Answer calculated = %d", S);
//         #10;

//         $finish;
//     end

//     initial begin
//         // $monitor("Time = %0t: A = %b, B = %b, C0 = %b,Cout = %b, S = %b", $time, A, B, C0, Cout, S);
//     end 
// endmodule

Q4_Adders/q4_cla.vcd
$date
	Fri Nov  1 17:54:29 2024
$end
$version
	Icarus Verilog
$end
$timescale
	1ns
$end
$scope module four_bit_cla_test $end
$var wire 4 ! S [3:0] $end
$var wire 1 " Cout $end
$var reg 4 # A [3:0] $end
$var reg 4 $ B [3:0] $end
$var reg 1 % C0 $end
$scope module uut $end
$var wire 4 & A [3:0] $end
$var wire 4 ' B [3:0] $end
$var wire 1 % C0 $end
$var wire 1 ( G0 $end
$var wire 1 ) G1 $end
$var wire 1 * G2 $end
$var wire 1 + G3 $end
$var wire 1 , P0 $end
$var wire 1 - P1 $end
$var wire 1 . P2 $end
$var wire 1 / P3 $end
$var wire 1 0 x1 $end
$var wire 1 1 x10 $end
$var wire 1 2 x2 $end
$var wire 1 3 x3 $end
$var wire 1 4 x4 $end
$var wire 1 5 x5 $end
$var wire 1 6 x6 $end
$var wire 1 7 x7 $end
$var wire 1 8 x8 $end
$var wire 1 9 x9 $end
$var wire 4 : S [3:0] $end
$var wire 1 " Cout $end
$var wire 5 ; C [4:0] $end
$upscope $end
$scope begin $ivl_for_loop0 $end
$var integer 32 < i [31:0] $end
$scope begin $ivl_for_loop1 $end
$var integer 32 = j [31:0] $end
$scope begin $ivl_for_loop2 $end
$var integer 32 > k [31:0] $end
$upscope $end
$upscope $end
$upscope $end
$upscope $end
$enddefinitions $end
#0
$dumpvars
b0 >
b0 =
b0 <
b0 ;
b0 :
09
08
07
06
05
04
03
02
01
00
0/
0.
0-
0,
0+
0*
0)
0(
b0 '
b0 &
0%
b0 $
b0 #
0"
b0 !
$end
#10
b1 !
b1 :
b1 ;
1%
b1 >
#20
1,
b0 ;
0%
b1 $
b1 '
b1 =
b0 >
#30
b10 !
b10 :
10
b11 ;
1%
b1 >
#40
b10 !
b10 :
0,
1-
00
b0 ;
0%
b10 $
b10 '
b10 =
b0 >
#50
b11 !
b11 :
b1 ;
1%
b1 >
#60
1,
b0 ;
0%
b11 $
b11 '
b11 =
b0 >
#70
b100 !
b100 :
10
13
b111 ;
1%
b1 >
#80
b100 !
b100 :
0,
0-
1.
00
03
b0 ;
0%
b100 $
b100 '
b100 =
b0 >
#90
b101 !
b101 :
b1 ;
1%
b1 >
#100
1,
b0 ;
0%
b101 $
b101 '
b101 =
b0 >
#110
b110 !
b110 :
10
b11 ;
1%
b1 >
#120
b110 !
b110 :
0,
1-
00
b0 ;
0%
b110 $
b110 '
b110 =
b0 >
#130
b111 !
b111 :
b1 ;
1%
b1 >
#140
1,
b0 ;
0%
b111 $
b111 '
b111 =
b0 >
#150
b1000 !
b1000 :
10
13
16
b1111 ;
1%
b1 >
#160
b1000 !
b1000 :
0,
0-
0.
1/
00
03
06
b0 ;
0%
b1000 $
b1000 '
b1000 =
b0 >
#170
b1001 !
b1001 :
b1 ;
1%
b1 >
#180
1,
b0 ;
0%
b1001 $
b1001 '
b1001 =
b0 >
#190
b1010 !
b1010 :
10
b11 ;
1%
b1 >
#200
b1010 !
b1010 :
0,
1-
00
b0 ;
0%
b1010 $
b1010 '
b1010 =
b0 >
#210
b1011 !
b1011 :
b1 ;
1%
b1 >
#220
1,
b0 ;
0%
b1011 $
b1011 '
b1011 =
b0 >
#230
b1100 !
b1100 :
10
13
b111 ;
1%
b1 >
#240
b1100 !
b1100 :
0,
0-
1.
00
03
b0 ;
0%
b1100 $
b1100 '
b1100 =
b0 >
#250
b1101 !
b1101 :
b1 ;
1%
b1 >
#260
1,
b0 ;
0%
b1101 $
b1101 '
b1101 =
b0 >
#270
b1110 !
b1110 :
10
b11 ;
1%
b1 >
#280
b1110 !
b1110 :
0,
1-
00
b0 ;
0%
b1110 $
b1110 '
b1110 =
b0 >
#290
b1111 !
b1111 :
b1 ;
1%
b1 >
#300
1,
b0 ;
0%
b1111 $
b1111 '
b1111 =
b0 >
#310
1"
11
b0 !
b0 :
10
13
16
b11111 ;
1%
b1 >
#320
0"
01
b1 !
b1 :
0-
0.
0/
00
03
06
b0 ;
0%
b0 $
b0 '
b1 #
b1 &
b1 <
b0 =
b0 >
#330
b10 !
b10 :
10
b11 ;
1%
b1 >
#340
0,
1(
00
b10 ;
0%
b1 $
b1 '
b1 =
b0 >
#350
b11 !
b11 :
b11 ;
1%
b1 >
#360
b11 !
b11 :
1,
1-
0(
b0 ;
0%
b10 $
b10 '
b10 =
b0 >
#370
b100 !
b100 :
10
13
b111 ;
1%
b1 >
#380
b100 !
b100 :
12
0,
1(
00
03
b110 ;
0%
b11 $
b11 '
b11 =
b0 >
#390
b101 !
b101 :
b111 ;
1%
b1 >
#400
b101 !
b101 :
02
1,
0-
1.
0(
b0 ;
0%
b100 $
b100 '
b100 =
b0 >
#410
b110 !
b110 :
10
b11 ;
1%
b1 >
#420
0,
1(
00
b10 ;
0%
b101 $
b101 '
b101 =
b0 >
#430
b111 !
b111 :
b11 ;
1%
b1 >
#440
b111 !
b111 :
1,
1-
0(
b0 ;
0%
b110 $
b110 '
b110 =
b0 >
#450
b1000 !
b1000 :
10
13
16
b1111 ;
1%
b1 >
#460
b1000 !
b1000 :
12
15
0,
1(
00
03
06
b1110 ;
0%
b111 $
b111 '
b111 =
b0 >
#470
b1001 !
b1001 :
b1111 ;
1%
b1 >
#480
b1001 !
b1001 :
02
05
1,
0-
0.
1/
0(
b0 ;
0%
b1000 $
b1000 '
b1000 =
b0 >
#490
b1010 !
b1010 :
10
b11 ;
1%
b1 >
#500
0,
1(
00
b10 ;
0%
b1001 $
b1001 '
b1001 =
b0 >
#510
b1011 !
b1011 :
b11 ;
1%
b1 >
#520
b1011 !
b1011 :
1,
1-
0(
b0 ;
0%
b1010 $
b1010 '
b1010 =
b0 >
#530
b1100 !
b1100 :
10
13
b111 ;
1%
b1 >
#540
b1100 !
b1100 :
12
0,
1(
00
03
b110 ;
0%
b1011 $
b1011 '
b1011 =
b0 >
#550
b1101 !
b1101 :
b111 ;
1%
b1 >
#560
b1101 !
b1101 :
02
1,
0-
1.
0(
b0 ;
0%
b1100 $
b1100 '
b1100 =
b0 >
#570
b1110 !
b1110 :
10
b11 ;
1%
b1 >
#580
0,
1(
00
b10 ;
0%
b1101 $
b1101 '
b1101 =
b0 >
#590
b1111 !
b1111 :
b11 ;
1%
b1 >
#600
b1111 !
b1111 :
1,
1-
0(
b0 ;
0%
b1110 $
b1110 '
b1110 =
b0 >
#610
1"
11
b0 !
b0 :
10
13
16
b11111 ;
1%
b1 >
#620
b0 !
b0 :
12
15
19
01
0,
1(
00
03
06
b11110 ;
0%
b1111 $
b1111 '
b1111 =
b0 >
#630
b1 !
b1 :
b11111 ;
1%
b1 >
#640
0"
02
05
09
b10 !
b10 :
0.
0/
0(
b0 ;
0%
b0 $
b0 '
b10 #
b10 &
b10 <
b0 =
b0 >
#650
b11 !
b11 :
b1 ;
1%
b1 >
#660
1,
b0 ;
0%
b1 $
b1 '
b1 =
b0 >
#670
b100 !
b100 :
10
13
b111 ;
1%
b1 >
#680
b100 !
b100 :
0,
0-
1)
00
03
b100 ;
0%
b10 $
b10 '
b10 =
b0 >
#690
b101 !
b101 :
b101 ;
1%
b1 >
#700
1,
b100 ;
0%
b11 $
b11 '
b11 =
b0 >
#710
b110 !
b110 :
10
b111 ;
1%
b1 >
#720
b110 !
b110 :
0,
1-
1.
0)
00
b0 ;
0%
b100 $
b100 '
b100 =
b0 >
#730
b111 !
b111 :
b1 ;
1%
b1 >
#740
1,
b0 ;
0%
b101 $
b101 '
b101 =
b0 >
#750
b1000 !
b1000 :
10
13
16
b1111 ;
1%
b1 >
#760
b1000 !
b1000 :
14
0,
0-
1)
00
03
06
b1100 ;
0%
b110 $
b110 '
b110 =
b0 >
#770
b1001 !
b1001 :
b1101 ;
1%
b1 >
#780
1,
b1100 ;
0%
b111 $
b111 '
b111 =
b0 >
#790
b1010 !
b1010 :
10
b1111 ;
1%
b1 >
#800
b1010 !
b1010 :
04
0,
1-
0.
1/
0)
00
b0 ;
0%
b1000 $
b1000 '
b1000 =
b0 >
#810
b1011 !
b1011 :
b1 ;
1%
b1 >
#820
1,
b0 ;
0%
b1001 $
b1001 '
b1001 =
b0 >
#830
b1100 !
b1100 :
10
13
b111 ;
1%
b1 >
#840
b1100 !
b1100 :
0,
0-
1)
00
03
b100 ;
0%
b1010 $
b1010 '
b1010 =
b0 >
#850
b1101 !
b1101 :
b101 ;
1%
b1 >
#860
1,
b100 ;
0%
b1011 $
b1011 '
b1011 =
b0 >
#870
b1110 !
b1110 :
10
b111 ;
1%
b1 >
#880
b1110 !
b1110 :
0,
1-
1.
0)
00
b0 ;
0%
b1100 $
b1100 '
b1100 =
b0 >
#890
b1111 !
b1111 :
b1 ;
1%
b1 >
#900
1,
b0 ;
0%
b1101 $
b1101 '
b1101 =
b0 >
#910
1"
11
b0 !
b0 :
10
13
16
b11111 ;
1%
b1 >
#920
b0 !
b0 :
14
18
01
0,
0-
1)
00
03
06
b11100 ;
0%
b1110 $
b1110 '
b1110 =
b0 >
#930
b1 !
b1 :
b11101 ;
1%
b1 >
#940
1,
b11100 ;
0%
b1111 $
b1111 '
b1111 =
b0 >
#950
b10 !
b10 :
10
b11111 ;
1%
b1 >
#960
0"
04
08
b11 !
b11 :
1-
0.
0/
0)
00
b0 ;
0%
b0 $
b0 '
b11 #
b11 &
b11 <
b0 =
b0 >
#970
b100 !
b100 :
10
13
b111 ;
1%
b1 >
#980
b100 !
b100 :
12
0,
1(
00
03
b110 ;
0%
b1 $
b1 '
b1 =
b0 >
#990
b101 !
b101 :
b111 ;
1%
b1 >
#1000
b101 !
b101 :
02
1,
0-
0(
1)
b100 ;
0%
b10 $
b10 '
b10 =
b0 >
#1010
b110 !
b110 :
10
b111 ;
1%
b1 >
#1020
0,
1(
00
b110 ;
0%
b11 $
b11 '
b11 =
b0 >
#1030
b111 !
b111 :
b111 ;
1%
b1 >
#1040
b111 !
b111 :
1,
1-
1.
0(
0)
b0 ;
0%
b100 $
b100 '
b100 =
b0 >
#1050
b1000 !
b1000 :
10
13
16
b1111 ;
1%
b1 >
#1060
b1000 !
b1000 :
12
15
0,
1(
00
03
06
b1110 ;
0%
b101 $
b101 '
b101 =
b0 >
#1070
b1001 !
b1001 :
b1111 ;
1%
b1 >
#1080
b1001 !
b1001 :
02
05
14
1,
0-
0(
1)
b1100 ;
0%
b110 $
b110 '
b110 =
b0 >
#1090
b1010 !
b1010 :
10
b1111 ;
1%
b1 >
#1100
0,
1(
00
b1110 ;
0%
b111 $
b111 '
b111 =
b0 >
#1110
b1011 !
b1011 :
b1111 ;
1%
b1 >
#1120
b1011 !
b1011 :
04
1,
1-
0.
1/
0(
0)
b0 ;
0%
b1000 $
b1000 '
b1000 =
b0 >
#1130
b1100 !
b1100 :
10
13
b111 ;
1%
b1 >
#1140
b1100 !
b1100 :
12
0,
1(
00
03
b110 ;
0%
b1001 $
b1001 '
b1001 =
b0 >
#1150
b1101 !
b1101 :
b111 ;
1%
b1 >
#1160
b1101 !
b1101 :
02
1,
0-
0(
1)
b100 ;
0%
b1010 $
b1010 '
b1010 =
b0 >
#1170
b1110 !
b1110 :
10
b111 ;
1%
b1 >
#1180
0,
1(
00
b110 ;
0%
b1011 $
b1011 '
b1011 =
b0 >
#1190
b1111 !
b1111 :
b111 ;
1%
b1 >
#1200
b1111 !
b1111 :
1,
1-
1.
0(
0)
b0 ;
0%
b1100 $
b1100 '
b1100 =
b0 >
#1210
1"
11
b0 !
b0 :
10
13
16
b11111 ;
1%
b1 >
#1220
b0 !
b0 :
12
15
19
01
0,
1(
00
03
06
b11110 ;
0%
b1101 $
b1101 '
b1101 =
b0 >
#1230
b1 !
b1 :
b11111 ;
1%
b1 >
#1240
b1 !
b1 :
02
05
09
14
18
1,
0-
0(
1)
b11100 ;
0%
b1110 $
b1110 '
b1110 =
b0 >
#1250
b10 !
b10 :
10
b11111 ;
1%
b1 >
#1260
0,
1(
00
b11110 ;
0%
b1111 $
b1111 '
b1111 =
b0 >
#1270
b11 !
b11 :
b11111 ;
1%
b1 >
#1280
0"
04
08
b100 !
b100 :
0/
0(
0)
b0 ;
0%
b0 $
b0 '
b100 #
b100 &
b100 <
b0 =
b0 >
#1290
b101 !
b101 :
b1 ;
1%
b1 >
#1300
1,
b0 ;
0%
b1 $
b1 '
b1 =
b0 >
#1310
b110 !
b110 :
10
b11 ;
1%
b1 >
#1320
b110 !
b110 :
0,
1-
00
b0 ;
0%
b10 $
b10 '
b10 =
b0 >
#1330
b111 !
b111 :
b1 ;
1%
b1 >
#1340
1,
b0 ;
0%
b11 $
b11 '
b11 =
b0 >
#1350
b1000 !
b1000 :
10
13
16
b1111 ;
1%
b1 >
#1360
b1000 !
b1000 :
0,
0-
0.
1*
00
03
06
b1000 ;
0%
b100 $
b100 '
b100 =
b0 >
#1370
b1001 !
b1001 :
b1001 ;
1%
b1 >
#1380
1,
b1000 ;
0%
b101 $
b101 '
b101 =
b0 >
#1390
b1010 !
b1010 :
10
b1011 ;
1%
b1 >
#1400
b1010 !
b1010 :
0,
1-
00
b1000 ;
0%
b110 $
b110 '
b110 =
b0 >
#1410
b1011 !
b1011 :
b1001 ;
1%
b1 >
#1420
1,
b1000 ;
0%
b111 $
b111 '
b111 =
b0 >
#1430
b1100 !
b1100 :
10
13
b1111 ;
1%
b1 >
#1440
b1100 !
b1100 :
0,
0-
1.
1/
0*
00
03
b0 ;
0%
b1000 $
b1000 '
b1000 =
b0 >
#1450
b1101 !
b1101 :
b1 ;
1%
b1 >
#1460
1,
b0 ;
0%
b1001 $
b1001 '
b1001 =
b0 >
#1470
b1110 !
b1110 :
10
b11 ;
1%
b1 >
#1480
b1110 !
b1110 :
0,
1-
00
b0 ;
0%
b1010 $
b1010 '
b1010 =
b0 >
#1490
b1111 !
b1111 :
b1 ;
1%
b1 >
#1500
1,
b0 ;
0%
b1011 $
b1011 '
b1011 =
b0 >
#1510
1"
11
b0 !
b0 :
10
13
16
b11111 ;
1%
b1 >
#1520
b0 !
b0 :
17
01
0,
0-
0.
1*
00
03
06
b11000 ;
0%
b1100 $
b1100 '
b1100 =
b0 >
#1530
b1 !
b1 :
b11001 ;
1%
b1 >
#1540
1,
b11000 ;
0%
b1101 $
b1101 '
b1101 =
b0 >
#1550
b10 !
b10 :
10
b11011 ;
1%
b1 >
#1560
b10 !
b10 :
0,
1-
00
b11000 ;
0%
b1110 $
b1110 '
b1110 =
b0 >
#1570
b11 !
b11 :
b11001 ;
1%
b1 >
#1580
1,
b11000 ;
0%
b1111 $
b1111 '
b1111 =
b0 >
#1590
b100 !
b100 :
10
13
b11111 ;
1%
b1 >
#1600
0"
07
b101 !
b101 :
0-
1.
0/
0*
00
03
b0 ;
0%
b0 $
b0 '
b101 #
b101 &
b101 <
b0 =
b0 >
#1610
b110 !
b110 :
10
b11 ;
1%
b1 >
#1620
0,
1(
00
b10 ;
0%
b1 $
b1 '
b1 =
b0 >
#1630
b111 !
b111 :
b11 ;
1%
b1 >
#1640
b111 !
b111 :
1,
1-
0(
b0 ;
0%
b10 $
b10 '
b10 =
b0 >
#1650
b1000 !
b1000 :
10
13
16
b1111 ;
1%
b1 >
#1660
b1000 !
b1000 :
12
15
0,
1(
00
03
06
b1110 ;
0%
b11 $
b11 '
b11 =
b0 >
#1670
b1001 !
b1001 :
b1111 ;
1%
b1 >
#1680
b1001 !
b1001 :
02
05
1,
0-
0.
0(
1*
b1000 ;
0%
b100 $
b100 '
b100 =
b0 >
#1690
b1010 !
b1010 :
10
b1011 ;
1%
b1 >
#1700
0,
1(
00
b1010 ;
0%
b101 $
b101 '
b101 =
b0 >
#1710
b1011 !
b1011 :
b1011 ;
1%
b1 >
#1720
b1011 !
b1011 :
1,
1-
0(
b1000 ;
0%
b110 $
b110 '
b110 =
b0 >
#1730
b1100 !
b1100 :
10
13
b1111 ;
1%
b1 >
#1740
b1100 !
b1100 :
12
0,
1(
00
03
b1110 ;
0%
b111 $
b111 '
b111 =
b0 >
#1750
b1101 !
b1101 :
b1111 ;
1%
b1 >
#1760
b1101 !
b1101 :
02
1,
0-
1.
1/
0(
0*
b0 ;
0%
b1000 $
b1000 '
b1000 =
b0 >
#1770
b1110 !
b1110 :
10
b11 ;
1%
b1 >
#1780
0,
1(
00
b10 ;
0%
b1001 $
b1001 '
b1001 =
b0 >
#1790
b1111 !
b1111 :
b11 ;
1%
b1 >
#1800
b1111 !
b1111 :
1,
1-
0(
b0 ;
0%
b1010 $
b1010 '
b1010 =
b0 >
#1810
1"
11
b0 !
b0 :
10
13
16
b11111 ;
1%
b1 >
#1820
b0 !
b0 :
12
15
19
01
0,
1(
00
03
06
b11110 ;
0%
b1011 $
b1011 '
b1011 =
b0 >
#1830
b1 !
b1 :
b11111 ;
1%
b1 >
#1840
b1 !
b1 :
02
05
09
17
1,
0-
0.
0(
1*
b11000 ;
0%
b1100 $
b1100 '
b1100 =
b0 >
#1850
b10 !
b10 :
10
b11011 ;
1%
b1 >
#1860
0,
1(
00
b11010 ;
0%
b1101 $
b1101 '
b1101 =
b0 >
#1870
b11 !
b11 :
b11011 ;
1%
b1 >
#1880
b11 !
b11 :
1,
1-
0(
b11000 ;
0%
b1110 $
b1110 '
b1110 =
b0 >
#1890
b100 !
b100 :
10
13
b11111 ;
1%
b1 >
#1900
b100 !
b100 :
12
0,
1(
00
03
b11110 ;
0%
b1111 $
b1111 '
b1111 =
b0 >
#1910
b101 !
b101 :
b11111 ;
1%
b1 >
#1920
0"
07
02
b110 !
b110 :
1.
0/
0*
0(
b0 ;
0%
b0 $
b0 '
b110 #
b110 &
b110 <
b0 =
b0 >
#1930
b111 !
b111 :
b1 ;
1%
b1 >
#1940
1,
b0 ;
0%
b1 $
b1 '
b1 =
b0 >
#1950
b1000 !
b1000 :
10
13
16
b1111 ;
1%
b1 >
#1960
b1000 !
b1000 :
14
0,
0-
1)
00
03
06
b1100 ;
0%
b10 $
b10 '
b10 =
b0 >
#1970
b1001 !
b1001 :
b1101 ;
1%
b1 >
#1980
1,
b1100 ;
0%
b11 $
b11 '
b11 =
b0 >
#1990
b1010 !
b1010 :
10
b1111 ;
1%
b1 >
#2000
b1010 !
b1010 :
04
0,
1-
0.
0)
1*
00
b1000 ;
0%
b100 $
b100 '
b100 =
b0 >
#2010
b1011 !
b1011 :
b1001 ;
1%
b1 >
#2020
1,
b1000 ;
0%
b101 $
b101 '
b101 =
b0 >
#2030
b1100 !
b1100 :
10
13
b1111 ;
1%
b1 >
#2040
b1100 !
b1100 :
0,
0-
1)
00
03
b1100 ;
0%
b110 $
b110 '
b110 =
b0 >
#2050
b1101 !
b1101 :
b1101 ;
1%
b1 >
#2060
1,
b1100 ;
0%
b111 $
b111 '
b111 =
b0 >
#2070
b1110 !
b1110 :
10
b1111 ;
1%
b1 >
#2080
b1110 !
b1110 :
0,
1-
1.
1/
0)
0*
00
b0 ;
0%
b1000 $
b1000 '
b1000 =
b0 >
#2090
b1111 !
b1111 :
b1 ;
1%
b1 >
#2100
1,
b0 ;
0%
b1001 $
b1001 '
b1001 =
b0 >
#2110
1"
11
b0 !
b0 :
10
13
16
b11111 ;
1%
b1 >
#2120
b0 !
b0 :
14
18
01
0,
0-
1)
00
03
06
b11100 ;
0%
b1010 $
b1010 '
b1010 =
b0 >
#2130
b1 !
b1 :
b11101 ;
1%
b1 >
#2140
1,
b11100 ;
0%
b1011 $
b1011 '
b1011 =
b0 >
#2150
b10 !
b10 :
10
b11111 ;
1%
b1 >
#2160
b10 !
b10 :
04
08
17
0,
1-
0.
0)
1*
00
b11000 ;
0%
b1100 $
b1100 '
b1100 =
b0 >
#2170
b11 !
b11 :
b11001 ;
1%
b1 >
#2180
1,
b11000 ;
0%
b1101 $
b1101 '
b1101 =
b0 >
#2190
b100 !
b100 :
10
13
b11111 ;
1%
b1 >
#2200
b100 !
b100 :
0,
0-
1)
00
03
b11100 ;
0%
b1110 $
b1110 '
b1110 =
b0 >
#2210
b101 !
b101 :
b11101 ;
1%
b1 >
#2220
1,
b11100 ;
0%
b1111 $
b1111 '
b1111 =
b0 >
#2230
b110 !
b110 :
10
b11111 ;
1%
b1 >
#2240
0"
07
b111 !
b111 :
1-
1.
0/
0)
0*
00
b0 ;
0%
b0 $
b0 '
b111 #
b111 &
b111 <
b0 =
b0 >
#2250
b1000 !
b1000 :
10
13
16
b1111 ;
1%
b1 >
#2260
b1000 !
b1000 :
12
15
0,
1(
00
03
06
b1110 ;
0%
b1 $
b1 '
b1 =
b0 >
#2270
b1001 !
b1001 :
b1111 ;
1%
b1 >
#2280
b1001 !
b1001 :
02
05
14
1,
0-
0(
1)
b1100 ;
0%
b10 $
b10 '
b10 =
b0 >
#2290
b1010 !
b1010 :
10
b1111 ;
1%
b1 >
#2300
0,
1(
00
b1110 ;
0%
b11 $
b11 '
b11 =
b0 >
#2310
b1011 !
b1011 :
b1111 ;
1%
b1 >
#2320
b1011 !
b1011 :
04
1,
1-
0.
0(
0)
1*
b1000 ;
0%
b100 $
b100 '
b100 =
b0 >
#2330
b1100 !
b1100 :
10
13
b1111 ;
1%
b1 >
#2340
b1100 !
b1100 :
12
0,
1(
00
03
b1110 ;
0%
b101 $
b101 '
b101 =
b0 >
#2350
b1101 !
b1101 :
b1111 ;
1%
b1 >
#2360
b1101 !
b1101 :
02
1,
0-
0(
1)
b1100 ;
0%
b110 $
b110 '
b110 =
b0 >
#2370
b1110 !
b1110 :
10
b1111 ;
1%
b1 >
#2380
0,
1(
00
b1110 ;
0%
b111 $
b111 '
b111 =
b0 >
#2390
b1111 !
b1111 :
b1111 ;
1%
b1 >
#2400
b1111 !
b1111 :
1,
1-
1.
1/
0(
0)
0*
b0 ;
0%
b1000 $
b1000 '
b1000 =
b0 >
#2410
1"
11
b0 !
b0 :
10
13
16
b11111 ;
1%
b1 >
#2420
b0 !
b0 :
12
15
19
01
0,
1(
00
03
06
b11110 ;
0%
b1001 $
b1001 '
b1001 =
b0 >
#2430
b1 !
b1 :
b11111 ;
1%
b1 >
#2440
b1 !
b1 :
02
05
09
14
18
1,
0-
0(
1)
b11100 ;
0%
b1010 $
b1010 '
b1010 =
b0 >
#2450
b10 !
b10 :
10
b11111 ;
1%
b1 >
#2460
0,
1(
00
b11110 ;
0%
b1011 $
b1011 '
b1011 =
b0 >
#2470
b11 !
b11 :
b11111 ;
1%
b1 >
#2480
b11 !
b11 :
04
08
17
1,
1-
0.
0(
0)
1*
b11000 ;
0%
b1100 $
b1100 '
b1100 =
b0 >
#2490
b100 !
b100 :
10
13
b11111 ;
1%
b1 >
#2500
b100 !
b100 :
12
0,
1(
00
03
b11110 ;
0%
b1101 $
b1101 '
b1101 =
b0 >
#2510
b101 !
b101 :
b11111 ;
1%
b1 >
#2520
b101 !
b101 :
02
1,
0-
0(
1)
b11100 ;
0%
b1110 $
b1110 '
b1110 =
b0 >
#2530
b110 !
b110 :
10
b11111 ;
1%
b1 >
#2540
0,
1(
00
b11110 ;
0%
b1111 $
b1111 '
b1111 =
b0 >
#2550
b111 !
b111 :
b11111 ;
1%
b1 >
#2560
0"
07
b1000 !
b1000 :
0(
0)
0*
b0 ;
0%
b0 $
b0 '
b1000 #
b1000 &
b1000 <
b0 =
b0 >
#2570
b1001 !
b1001 :
b1 ;
1%
b1 >
#2580
1,
b0 ;
0%
b1 $
b1 '
b1 =
b0 >
#2590
b1010 !
b1010 :
10
b11 ;
1%
b1 >
#2600
b1010 !
b1010 :
0,
1-
00
b0 ;
0%
b10 $
b10 '
b10 =
b0 >
#2610
b1011 !
b1011 :
b1 ;
1%
b1 >
#2620
1,
b0 ;
0%
b11 $
b11 '
b11 =
b0 >
#2630
b1100 !
b1100 :
10
13
b111 ;
1%
b1 >
#2640
b1100 !
b1100 :
0,
0-
1.
00
03
b0 ;
0%
b100 $
b100 '
b100 =
b0 >
#2650
b1101 !
b1101 :
b1 ;
1%
b1 >
#2660
1,
b0 ;
0%
b101 $
b101 '
b101 =
b0 >
#2670
b1110 !
b1110 :
10
b11 ;
1%
b1 >
#2680
b1110 !
b1110 :
0,
1-
00
b0 ;
0%
b110 $
b110 '
b110 =
b0 >
#2690
b1111 !
b1111 :
b1 ;
1%
b1 >
#2700
1,
b0 ;
0%
b111 $
b111 '
b111 =
b0 >
#2710
1"
11
b0 !
b0 :
10
13
16
b11111 ;
1%
b1 >
#2720
b0 !
b0 :
01
0,
0-
0.
0/
1+
00
03
06
b10000 ;
0%
b1000 $
b1000 '
b1000 =
b0 >
#2730
b1 !
b1 :
b10001 ;
1%
b1 >
#2740
1,
b10000 ;
0%
b1001 $
b1001 '
b1001 =
b0 >
#2750
b10 !
b10 :
10
b10011 ;
1%
b1 >
#2760
b10 !
b10 :
0,
1-
00
b10000 ;
0%
b1010 $
b1010 '
b1010 =
b0 >
#2770
b11 !
b11 :
b10001 ;
1%
b1 >
#2780
1,
b10000 ;
0%
b1011 $
b1011 '
b1011 =
b0 >
#2790
b100 !
b100 :
10
13
b10111 ;
1%
b1 >
#2800
b100 !
b100 :
0,
0-
1.
00
03
b10000 ;
0%
b1100 $
b1100 '
b1100 =
b0 >
#2810
b101 !
b101 :
b10001 ;
1%
b1 >
#2820
1,
b10000 ;
0%
b1101 $
b1101 '
b1101 =
b0 >
#2830
b110 !
b110 :
10
b10011 ;
1%
b1 >
#2840
b110 !
b110 :
0,
1-
00
b10000 ;
0%
b1110 $
b1110 '
b1110 =
b0 >
#2850
b111 !
b111 :
b10001 ;
1%
b1 >
#2860
1,
b10000 ;
0%
b1111 $
b1111 '
b1111 =
b0 >
#2870
b1000 !
b1000 :
10
13
16
b11111 ;
1%
b1 >
