Q3_Mux_Demux_Decoders/Mux/q3_mux_design.v
`timescale 1ns/1ns

module mux_2x1(input A, input B, input S, output Y_2x1);
    assign Y_2x1 = ((~S) & A) | (S & B);
endmodule

module mux_4x1(input A, input B, input C, input D, input [1:0] S, output Y_4x1);
    mux_2x1 mux_2x1_1(.A(A), .B(B), .S(S[0]), .Y_2x1(Y1));
    mux_2x1 mux_2x1_2(.A(C), .B(D), .S(S[0]), .Y_2x1(Y2));
    mux_2x1 mux_2x1_3(.A(Y1), .B(Y2), .S(S[1]), .Y_2x1(Y_4x1));
endmodule

module mux_8x1(input A, input B, input C, input D, input E, input F, input G, input H, input [2:0] S, output Y_8x1);
    mux_4x1 mux_4x1_1(.A(A), .B(B), .C(C), .D(D), .S(S[1:0]), .Y_4x1(Y1));
    mux_4x1 mux_4x1_2(.A(E), .B(F), .C(G), .D(H), .S(S[1:0]), .Y_4x1(Y2));
    mux_2x1 mux_2x1_1(.A(Y1), .B(Y2), .S(S[2]), .Y_2x1(Y_8x1));
endmodule

Q3_Mux_Demux_Decoders/Mux/q3_mux_tb.v
`timescale 1ns/1ns

`include "q3_mux_design.v"

module mux_2x1_test;
    reg A, B, S;

    mux_2x1 uut(
        .A(A),
        .B(B),
        .S(S),
        .Y_2x1(Y_2x1)
    );

    initial begin
        $dumpfile("q3_mux.vcd");
        $dumpvars(0, mux_2x1_test);

        for (integer i = 0;i< 2;i = i+1)
        begin
            for (integer j = 0;j< 2;j = j+1)
            begin
                for (integer k = 0;k< 2;k = k+1)
                begin
                    A = i; B = j; S = k;
                    #10;
                end                
            end
        end
        $finish;
    end

    initial begin
        $monitor("Time = %0t: A = %b, B = %b, S = %b, Y_2x1 = %b", 
        $time, A, B, S, Y_2x1);
    end
endmodule

module mux_4x1_test;
    reg A, B, C, D;
    reg [1:0] S;

    mux_4x1 uut(
        .A(A),
        .B(B),
        .C(C),
        .D(D),
        .S(S),
        .Y_4x1(Y_4x1)
    );

    initial begin
        $dumpfile("q3_mux.vcd");
        $dumpvars(0, mux_4x1_test);

        for (integer i = 0;i< 2;i = i+1)
        begin
            for (integer j = 0;j< 2;j = j+1)
            begin
                for (integer k = 0;k< 2;k = k+1)
                begin
                    for (integer l = 0;l< 2;l = l+1)
                    begin
                        for (integer m = 0;m< 4;m = m+1)
                        begin
                            A = i; B = j; C = k; D = l; S = m;
                            #10;
                        end
                    end
                end
            end
        end
        $finish;
    end

    initial begin
        $monitor("Time = %0t: A = %b, B = %b, C = %b, D = %b, S = %b%b Y_4x1 = %b", 
        $time, A, B, C, D, S[1], S[0], Y_4x1);
    end

endmodule

module mux_8x1_test;
    reg A, B, C, D, E, F, G, H;
    reg [2:0] S;

    mux_8x1 uut(
        .A(A),
        .B(B),
        .C(C),
        .D(D),
        .E(E),
        .F(F),
        .G(G),
        .H(H),
        .S(S),
        .Y_8x1(Y_8x1)
    );

    initial begin
        $dumpfile("q3_mux.vcd");
        $dumpvars(0, mux_8x1_test);

        for (integer i = 0;i< 2;i = i+1)
        begin
            for (integer j = 0;j< 2;j = j+1)
            begin
                for (integer k = 0;k< 2;k = k+1)
                begin
                    for (integer l = 0;l< 2;l = l+1)
                    begin
                        for (integer m = 0;m< 2;m = m+1)
                        begin
                            for (integer n = 0;n< 2;n = n+1)
                            begin
                                for (integer o = 0;o< 2;o = o+1)
                                begin
                                    for (integer p = 0;p< 2;p = p+1)
                                    begin
                                        for (integer q = 0;q< 8;q = q+1)
                                        begin
                                            A = i; B = j; C = k; D = l; E = m; F = n; G = o; H = p; S = q;
                                            #10;
                                        end
                                    end
                                end
                            end
                        end
                    end
                end
            end
        end
        $finish;
    end

    initial begin
        $monitor("Time = %0t: A = %b, B = %b, C = %b, D = %b, E = %b, F = %b, G = %b, H = %b, S = %b%b%b Y_8x1 = %b", 
        $time, A, B, C, D, E, F, G, H, S[2], S[1], S[0], Y_8x1);
    end
endmodule

Q3_Mux_Demux_Decoders/Mux/q3_mux.vcd
$date
	Wed Oct  2 21:37:05 2024
$end
$version
	Icarus Verilog
$end
$timescale
	1ns
$end
$scope module mux_8x1_test $end
$var wire 1 ! Y_8x1 $end
$var reg 1 " A $end
$var reg 1 # B $end
$var reg 1 $ C $end
$var reg 1 % D $end
$var reg 1 & E $end
$var reg 1 ' F $end
$var reg 1 ( G $end
$var reg 1 ) H $end
$var reg 3 * S [2:0] $end
$scope module uut $end
$var wire 1 " A $end
$var wire 1 # B $end
$var wire 1 $ C $end
$var wire 1 % D $end
$var wire 1 & E $end
$var wire 1 ' F $end
$var wire 1 ( G $end
$var wire 1 ) H $end
$var wire 3 + S [2:0] $end
$var wire 1 ! Y_8x1 $end
$var wire 1 , Y2 $end
$var wire 1 - Y1 $end
$scope module mux_2x1_1 $end
$var wire 1 . S $end
$var wire 1 ! Y_2x1 $end
$var wire 1 , B $end
$var wire 1 - A $end
$upscope $end
$scope module mux_4x1_1 $end
$var wire 1 " A $end
$var wire 1 # B $end
$var wire 1 $ C $end
$var wire 1 % D $end
$var wire 2 / S [1:0] $end
$var wire 1 - Y_4x1 $end
$var wire 1 0 Y2 $end
$var wire 1 1 Y1 $end
$scope module mux_2x1_1 $end
$var wire 1 " A $end
$var wire 1 # B $end
$var wire 1 2 S $end
$var wire 1 1 Y_2x1 $end
$upscope $end
$scope module mux_2x1_2 $end
$var wire 1 $ A $end
$var wire 1 % B $end
$var wire 1 3 S $end
$var wire 1 0 Y_2x1 $end
$upscope $end
$scope module mux_2x1_3 $end
$var wire 1 1 A $end
$var wire 1 0 B $end
$var wire 1 4 S $end
$var wire 1 - Y_2x1 $end
$upscope $end
$upscope $end
$scope module mux_4x1_2 $end
$var wire 1 & A $end
$var wire 1 ' B $end
$var wire 1 ( C $end
$var wire 1 ) D $end
$var wire 2 5 S [1:0] $end
$var wire 1 , Y_4x1 $end
$var wire 1 6 Y2 $end
$var wire 1 7 Y1 $end
$scope module mux_2x1_1 $end
$var wire 1 & A $end
$var wire 1 ' B $end
$var wire 1 8 S $end
$var wire 1 7 Y_2x1 $end
$upscope $end
$scope module mux_2x1_2 $end
$var wire 1 ( A $end
$var wire 1 ) B $end
$var wire 1 9 S $end
$var wire 1 6 Y_2x1 $end
$upscope $end
$scope module mux_2x1_3 $end
$var wire 1 7 A $end
$var wire 1 6 B $end
$var wire 1 : S $end
$var wire 1 , Y_2x1 $end
$upscope $end
$upscope $end
$upscope $end
$scope begin $ivl_for_loop0 $end
$var integer 32 ; i [31:0] $end
$scope begin $ivl_for_loop1 $end
$var integer 32 < j [31:0] $end
$scope begin $ivl_for_loop2 $end
$var integer 32 = k [31:0] $end
$scope begin $ivl_for_loop3 $end
$var integer 32 > l [31:0] $end
$scope begin $ivl_for_loop4 $end
$var integer 32 ? m [31:0] $end
$scope begin $ivl_for_loop5 $end
$var integer 32 @ n [31:0] $end
$scope begin $ivl_for_loop6 $end
$var integer 32 A o [31:0] $end
$scope begin $ivl_for_loop7 $end
$var integer 32 B p [31:0] $end
$scope begin $ivl_for_loop8 $end
$var integer 32 C q [31:0] $end
$upscope $end
$upscope $end
$upscope $end
$upscope $end
$upscope $end
$upscope $end
$upscope $end
$upscope $end
$upscope $end
$upscope $end
$enddefinitions $end
#0
$dumpvars
b0 C
b0 B
b0 A
b0 @
b0 ?
b0 >
b0 =
b0 <
b0 ;
0:
09
08
07
06
b0 5
04
03
02
01
00
b0 /
0.
0-
0,
b0 +
b0 *
0)
0(
0'
0&
0%
0$
0#
0"
0!
$end
#10
12
13
18
19
b1 /
b1 5
b1 *
b1 +
b1 C
#20
02
03
14
08
09
1:
b10 /
b10 5
b10 *
b10 +
b10 C
#30
12
13
18
19
b11 /
b11 5
b11 *
b11 +
b11 C
#40
02
03
04
08
09
0:
b0 /
b0 5
1.
b100 *
b100 +
b100 C
#50
12
13
18
19
b1 /
b1 5
b101 *
b101 +
b101 C
#60
02
03
14
08
09
1:
b10 /
b10 5
b110 *
b110 +
b110 C
#70
12
13
18
19
b11 /
b11 5
b111 *
b111 +
b111 C
#80
02
03
04
08
09
0:
06
b0 /
b0 5
0.
b0 *
b0 +
1)
b1 B
b0 C
#90
16
12
13
18
19
b1 /
b1 5
b1 *
b1 +
b1 C
#100
06
0,
02
03
14
08
09
1:
b10 /
b10 5
b10 *
b10 +
b10 C
#110
1,
16
12
13
18
19
b11 /
b11 5
b11 *
b11 +
b11 C
#120
06
0,
0!
02
03
04
08
09
0:
b0 /
b0 5
1.
b100 *
b100 +
b100 C
#130
16
12
13
18
19
b1 /
b1 5
b101 *
b101 +
b101 C
#140
0!
06
0,
02
03
14
08
09
1:
b10 /
b10 5
b110 *
b110 +
b110 C
#150
1!
1,
16
12
13
18
19
b11 /
b11 5
b111 *
b111 +
b111 C
#160
0,
0!
02
03
04
08
09
0:
16
b0 /
b0 5
0.
b0 *
b0 +
0)
1(
b1 A
b0 B
b0 C
#170
06
12
13
18
19
b1 /
b1 5
b1 *
b1 +
b1 C
#180
1,
16
02
03
14
08
09
1:
b10 /
b10 5
b10 *
b10 +
b10 C
#190
0,
06
12
13
18
19
b11 /
b11 5
b11 *
b11 +
b11 C
#200
16
02
03
04
08
09
0:
b0 /
b0 5
1.
b100 *
b100 +
b100 C
#210
06
12
13
18
19
b1 /
b1 5
b101 *
b101 +
b101 C
#220
1!
1,
16
02
03
14
08
09
1:
b10 /
b10 5
b110 *
b110 +
b110 C
#230
0!
0,
06
12
13
18
19
b11 /
b11 5
b111 *
b111 +
b111 C
#240
02
03
04
08
09
0:
16
b0 /
b0 5
0.
b0 *
b0 +
1)
b1 B
b0 C
#250
12
13
18
19
b1 /
b1 5
b1 *
b1 +
b1 C
#260
16
1,
02
03
14
08
09
1:
b10 /
b10 5
b10 *
b10 +
b10 C
#270
12
13
18
19
b11 /
b11 5
b11 *
b11 +
b11 C
#280
16
0,
0!
02
03
04
08
09
0:
b0 /
b0 5
1.
b100 *
b100 +
b100 C
#290
12
13
18
19
b1 /
b1 5
b101 *
b101 +
b101 C
#300
1!
16
1,
02
03
14
08
09
1:
b10 /
b10 5
b110 *
b110 +
b110 C
#310
12
13
18
19
b11 /
b11 5
b111 *
b111 +
b111 C
#320
0,
0!
02
03
04
08
09
0:
06
07
b0 /
b0 5
0.
b0 *
b0 +
0)
0(
1'
b1 @
b0 A
b0 B
b0 C
#330
1,
17
12
13
18
19
b1 /
b1 5
b1 *
b1 +
b1 C
#340
0,
07
02
03
14
08
09
1:
b10 /
b10 5
b10 *
b10 +
b10 C
#350
17
12
13
18
19
b11 /
b11 5
b11 *
b11 +
b11 C
#360
0!
0,
07
02
03
04
08
09
0:
b0 /
b0 5
1.
b100 *
b100 +
b100 C
#370
1!
1,
17
12
13
18
19
b1 /
b1 5
b101 *
b101 +
b101 C
#380
0!
0,
07
02
03
14
08
09
1:
b10 /
b10 5
b110 *
b110 +
b110 C
#390
17
12
13
18
19
b11 /
b11 5
b111 *
b111 +
b111 C
#400
0,
07
02
03
04
08
09
0:
06
b0 /
b0 5
0.
b0 *
b0 +
1)
b1 B
b0 C
#410
1,
17
16
12
13
18
19
b1 /
b1 5
b1 *
b1 +
b1 C
#420
0,
07
06
02
03
14
08
09
1:
b10 /
b10 5
b10 *
b10 +
b10 C
#430
1,
17
16
12
13
18
19
b11 /
b11 5
b11 *
b11 +
b11 C
#440
07
06
0,
0!
02
03
04
08
09
0:
b0 /
b0 5
1.
b100 *
b100 +
b100 C
#450
1!
1,
17
16
12
13
18
19
b1 /
b1 5
b101 *
b101 +
b101 C
#460
0!
0,
07
06
02
03
14
08
09
1:
b10 /
b10 5
b110 *
b110 +
b110 C
#470
1!
1,
17
16
12
13
18
19
b11 /
b11 5
b111 *
b111 +
b111 C
#480
07
0,
0!
02
03
04
08
09
0:
16
b0 /
b0 5
0.
b0 *
b0 +
0)
1(
b1 A
b0 B
b0 C
#490
1,
06
17
12
13
18
19
b1 /
b1 5
b1 *
b1 +
b1 C
#500
16
1,
07
02
03
14
08
09
1:
b10 /
b10 5
b10 *
b10 +
b10 C
#510
0,
06
17
12
13
18
19
b11 /
b11 5
b11 *
b11 +
b11 C
#520
0!
16
0,
07
02
03
04
08
09
0:
b0 /
b0 5
1.
b100 *
b100 +
b100 C
#530
1!
1,
06
17
12
13
18
19
b1 /
b1 5
b101 *
b101 +
b101 C
#540
1!
16
1,
07
02
03
14
08
09
1:
b10 /
b10 5
b110 *
b110 +
b110 C
#550
0!
0,
06
17
12
13
18
19
b11 /
b11 5
b111 *
b111 +
b111 C
#560
0,
07
02
03
04
08
09
0:
16
b0 /
b0 5
0.
b0 *
b0 +
1)
b1 B
b0 C
#570
1,
17
12
13
18
19
b1 /
b1 5
b1 *
b1 +
b1 C
#580
1,
07
16
02
03
14
08
09
1:
b10 /
b10 5
b10 *
b10 +
b10 C
#590
17
12
13
18
19
b11 /
b11 5
b11 *
b11 +
b11 C
#600
07
16
0,
0!
02
03
04
08
09
0:
b0 /
b0 5
1.
b100 *
b100 +
b100 C
#610
1!
1,
17
12
13
18
19
b1 /
b1 5
b101 *
b101 +
b101 C
#620
1!
1,
07
16
02
03
14
08
09
1:
b10 /
b10 5
b110 *
b110 +
b110 C
#630
17
12
13
18
19
b11 /
b11 5
b111 *
b111 +
b111 C
#640
1,
0!
02
03
04
08
09
0:
06
17
b0 /
b0 5
0.
b0 *
b0 +
0)
0(
0'
1&
b1 ?
b0 @
b0 A
b0 B
b0 C
#650
0,
07
12
13
18
19
b1 /
b1 5
b1 *
b1 +
b1 C
#660
17
02
03
14
08
09
1:
b10 /
b10 5
b10 *
b10 +
b10 C
#670
07
12
13
18
19
b11 /
b11 5
b11 *
b11 +
b11 C
#680
1!
1,
17
02
03
04
08
09
0:
b0 /
b0 5
1.
b100 *
b100 +
b100 C
#690
0!
0,
07
12
13
18
19
b1 /
b1 5
b101 *
b101 +
b101 C
#700
17
02
03
14
08
09
1:
b10 /
b10 5
b110 *
b110 +
b110 C
#710
07
12
13
18
19
b11 /
b11 5
b111 *
b111 +
b111 C
#720
1,
17
02
03
04
08
09
0:
06
b0 /
b0 5
0.
b0 *
b0 +
1)
b1 B
b0 C
#730
0,
07
16
12
13
18
19
b1 /
b1 5
b1 *
b1 +
b1 C
#740
17
06
0,
02
03
14
08
09
1:
b10 /
b10 5
b10 *
b10 +
b10 C
#750
1,
07
16
12
13
18
19
b11 /
b11 5
b11 *
b11 +
b11 C
#760
17
06
1,
1!
02
03
04
08
09
0:
b0 /
b0 5
1.
b100 *
b100 +
b100 C
#770
0!
0,
07
16
12
13
18
19
b1 /
b1 5
b101 *
b101 +
b101 C
#780
0!
17
06
0,
02
03
14
08
09
1:
b10 /
b10 5
b110 *
b110 +
b110 C
#790
1!
1,
07
16
12
13
18
19
b11 /
b11 5
b111 *
b111 +
b111 C
#800
17
1,
0!
02
03
04
08
09
0:
16
b0 /
b0 5
0.
b0 *
b0 +
0)
1(
b1 A
b0 B
b0 C
#810
0,
07
06
12
13
18
19
b1 /
b1 5
b1 *
b1 +
b1 C
#820
1,
17
16
02
03
14
08
09
1:
b10 /
b10 5
b10 *
b10 +
b10 C
#830
0,
07
06
12
13
18
19
b11 /
b11 5
b11 *
b11 +
b11 C
#840
1!
1,
17
16
02
03
04
08
09
0:
b0 /
b0 5
1.
b100 *
b100 +
b100 C
#850
0!
0,
07
06
12
13
18
19
b1 /
b1 5
b101 *
b101 +
b101 C
#860
1!
1,
17
16
02
03
14
08
09
1:
b10 /
b10 5
b110 *
b110 +
b110 C
#870
0!
0,
07
06
12
13
18
19
b11 /
b11 5
b111 *
b111 +
b111 C
#880
1,
17
02
03
04
08
09
0:
16
b0 /
b0 5
0.
b0 *
b0 +
1)
b1 B
b0 C
#890
0,
07
12
13
18
19
b1 /
b1 5
b1 *
b1 +
b1 C
#900
17
16
1,
02
03
14
08
09
1:
b10 /
b10 5
b10 *
b10 +
b10 C
#910
07
12
13
18
19
b11 /
b11 5
b11 *
b11 +
b11 C
#920
17
16
1,
1!
02
03
04
08
09
0:
b0 /
b0 5
1.
b100 *
b100 +
b100 C
#930
0!
0,
07
12
13
18
19
b1 /
b1 5
b101 *
b101 +
b101 C
#940
1!
17
16
1,
02
03
14
08
09
1:
b10 /
b10 5
b110 *
b110 +
b110 C
#950
07
12
13
18
19
b11 /
b11 5
b111 *
b111 +
b111 C
#960
1,
0!
02
03
04
08
09
0:
06
17
b0 /
b0 5
0.
b0 *
b0 +
0)
0(
1'
b1 @
b0 A
b0 B
b0 C
#970
12
13
18
19
b1 /
b1 5
b1 *
b1 +
b1 C
#980
0,
17
02
03
14
08
09
1:
b10 /
b10 5
b10 *
b10 +
b10 C
#990
12
13
18
19
b11 /
b11 5
b11 *
b11 +
b11 C
#1000
1!
1,
17
02
03
04
08
09
0:
b0 /
b0 5
1.
b100 *
b100 +
b100 C
#1010
12
13
18
19
b1 /
b1 5
b101 *
b101 +
b101 C
#1020
0!
0,
17
02
03
14
08
09
1:
b10 /
b10 5
b110 *
b110 +
b110 C
#1030
12
13
18
19
b11 /
b11 5
b111 *
b111 +
b111 C
#1040
1,
17
02
03
04
08
09
0:
06
b0 /
b0 5
0.
b0 *
b0 +
1)
b1 B
b0 C
#1050
16
12
13
18
19
b1 /
b1 5
b1 *
b1 +
b1 C
#1060
0,
17
06
02
03
14
08
09
1:
b10 /
b10 5
b10 *
b10 +
b10 C
#1070
1,
16
12
13
18
19
b11 /
b11 5
b11 *
b11 +
b11 C
#1080
17
06
1,
1!
02
03
04
08
09
0:
b0 /
b0 5
1.
b100 *
b100 +
b100 C
#1090
16
12
13
18
19
b1 /
b1 5
b101 *
b101 +
b101 C
#1100
0!
0,
17
06
02
03
14
08
09
1:
b10 /
b10 5
b110 *
b110 +
b110 C
#1110
1!
1,
16
12
13
18
19
b11 /
b11 5
b111 *
b111 +
b111 C
#1120
17
1,
0!
02
03
04
08
09
0:
16
b0 /
b0 5
0.
b0 *
b0 +
0)
1(
b1 A
b0 B
b0 C
#1130
06
12
13
18
19
b1 /
b1 5
b1 *
b1 +
b1 C
#1140
16
1,
17
02
03
14
08
09
1:
b10 /
b10 5
b10 *
b10 +
b10 C
#1150
0,
06
12
13
18
19
b11 /
b11 5
b11 *
b11 +
b11 C
#1160
1!
16
1,
17
02
03
04
08
09
0:
b0 /
b0 5
1.
b100 *
b100 +
b100 C
#1170
06
12
13
18
19
b1 /
b1 5
b101 *
b101 +
b101 C
#1180
1!
16
1,
17
02
03
14
08
09
1:
b10 /
b10 5
b110 *
b110 +
b110 C
#1190
0!
0,
06
12
13
18
19
b11 /
b11 5
b111 *
b111 +
b111 C
#1200
1,
17
02
03
04
08
09
0:
16
b0 /
b0 5
0.
b0 *
b0 +
1)
b1 B
b0 C
#1210
12
13
18
19
b1 /
b1 5
b1 *
b1 +
b1 C
#1220
1,
17
16
02
03
14
08
09
1:
b10 /
b10 5
b10 *
b10 +
b10 C
#1230
12
13
18
19
b11 /
b11 5
b11 *
b11 +
b11 C
#1240
17
16
1,
1!
02
03
04
08
09
0:
b0 /
b0 5
1.
b100 *
b100 +
b100 C
#1250
12
13
18
19
b1 /
b1 5
b101 *
b101 +
b101 C
#1260
1!
1,
17
16
02
03
14
08
09
1:
b10 /
b10 5
b110 *
b110 +
b110 C
#1270
12
13
18
19
b11 /
b11 5
b111 *
b111 +
b111 C
#1280
0,
0!
02
03
04
08
09
0:
06
07
00
b0 /
b0 5
0.
b0 *
b0 +
0)
0(
0'
0&
1%
b1 >
b0 ?
b0 @
b0 A
b0 B
b0 C
#1290
10
12
13
18
19
b1 /
b1 5
b1 *
b1 +
b1 C
#1300
0!
00
0-
02
03
14
08
09
1:
b10 /
b10 5
b10 *
b10 +
b10 C
#1310
1!
1-
10
12
13
18
19
b11 /
b11 5
b11 *
b11 +
b11 C
#1320
00
0-
0!
02
03
04
08
09
0:
b0 /
b0 5
1.
b100 *
b100 +
b100 C
#1330
10
12
13
18
19
b1 /
b1 5
b101 *
b101 +
b101 C
#1340
00
0-
02
03
14
08
09
1:
b10 /
b10 5
b110 *
b110 +
b110 C
#1350
1-
10
12
13
18
19
b11 /
b11 5
b111 *
b111 +
b111 C
#1360
00
0-
0!
02
03
04
08
09
0:
06
b0 /
b0 5
0.
b0 *
b0 +
1)
b1 B
b0 C
#1370
10
16
12
13
18
19
b1 /
b1 5
b1 *
b1 +
b1 C
#1380
0!
00
0-
06
0,
02
03
14
08
09
1:
b10 /
b10 5
b10 *
b10 +
b10 C
#1390
1!
1-
1,
10
16
12
13
18
19
b11 /
b11 5
b11 *
b11 +
b11 C
#1400
0!
00
0-
06
0,
02
03
04
08
09
0:
b0 /
b0 5
1.
b100 *
b100 +
b100 C
#1410
10
16
12
13
18
19
b1 /
b1 5
b101 *
b101 +
b101 C
#1420
0!
00
0-
06
0,
02
03
14
08
09
1:
b10 /
b10 5
b110 *
b110 +
b110 C
#1430
1!
1-
1,
10
16
12
13
18
19
b11 /
b11 5
b111 *
b111 +
b111 C
#1440
00
0-
0,
0!
02
03
04
08
09
0:
16
b0 /
b0 5
0.
b0 *
b0 +
0)
1(
b1 A
b0 B
b0 C
#1450
06
10
12
13
18
19
b1 /
b1 5
b1 *
b1 +
b1 C
#1460
1,
0!
16
00
0-
02
03
14
08
09
1:
b10 /
b10 5
b10 *
b10 +
b10 C
#1470
1!
0,
1-
06
10
12
13
18
19
b11 /
b11 5
b11 *
b11 +
b11 C
#1480
16
00
0-
0!
02
03
04
08
09
0:
b0 /
b0 5
1.
b100 *
b100 +
b100 C
#1490
06
10
12
13
18
19
b1 /
b1 5
b101 *
b101 +
b101 C
#1500
1!
1,
16
00
0-
02
03
14
08
09
1:
b10 /
b10 5
b110 *
b110 +
b110 C
#1510
0!
0,
1-
06
10
12
13
18
19
b11 /
b11 5
b111 *
b111 +
b111 C
#1520
00
0-
0!
02
03
04
08
09
0:
16
b0 /
b0 5
0.
b0 *
b0 +
1)
b1 B
b0 C
#1530
10
12
13
18
19
b1 /
b1 5
b1 *
b1 +
b1 C
#1540
0!
00
0-
16
1,
02
03
14
08
09
1:
b10 /
b10 5
b10 *
b10 +
b10 C
#1550
1!
1-
10
12
13
18
19
b11 /
b11 5
b11 *
b11 +
b11 C
#1560
0!
00
0-
16
0,
02
03
04
08
09
0:
b0 /
b0 5
1.
b100 *
b100 +
b100 C
#1570
10
12
13
18
19
b1 /
b1 5
b101 *
b101 +
b101 C
#1580
1!
00
0-
16
1,
02
03
14
08
09
1:
b10 /
b10 5
b110 *
b110 +
b110 C
#1590
1-
10
12
13
18
19
b11 /
b11 5
b111 *
b111 +
b111 C
#1600
00
0-
0,
0!
02
03
04
08
09
0:
06
07
b0 /
b0 5
0.
b0 *
b0 +
0)
0(
1'
b1 @
b0 A
b0 B
b0 C
#1610
1,
10
17
12
13
18
19
b1 /
b1 5
b1 *
b1 +
b1 C
#1620
0!
0,
00
0-
07
02
03
14
08
09
1:
b10 /
b10 5
b10 *
b10 +
b10 C
#1630
1!
1-
10
17
12
13
18
19
b11 /
b11 5
b11 *
b11 +
b11 C
#1640
0,
00
0-
07
0!
02
03
04
08
09
0:
b0 /
b0 5
1.
b100 *
b100 +
b100 C
#1650
1!
1,
10
17
12
13
18
19
b1 /
b1 5
b101 *
b101 +
b101 C
#1660
0!
0,
00
0-
07
02
03
14
08
09
1:
b10 /
b10 5
b110 *
b110 +
b110 C
#1670
1-
10
17
12
13
18
19
b11 /
b11 5
b111 *
b111 +
b111 C
#1680
0,
00
0-
07
0!
02
03
04
08
09
0:
06
b0 /
b0 5
0.
b0 *
b0 +
1)
b1 B
b0 C
#1690
1,
10
17
16
12
13
18
19
b1 /
b1 5
b1 *
b1 +
b1 C
#1700
0!
0,
00
0-
07
06
02
03
14
08
09
1:
b10 /
b10 5
b10 *
b10 +
b10 C
#1710
1!
1-
1,
10
17
16
12
13
18
19
b11 /
b11 5
b11 *
b11 +
b11 C
#1720
0!
00
0-
07
06
0,
02
03
04
08
09
0:
b0 /
b0 5
1.
b100 *
b100 +
b100 C
#1730
1!
1,
10
17
16
12
13
18
19
b1 /
b1 5
b101 *
b101 +
b101 C
#1740
0!
0,
00
0-
07
06
02
03
14
08
09
1:
b10 /
b10 5
b110 *
b110 +
b110 C
#1750
1!
1-
1,
10
17
16
12
13
18
19
b11 /
b11 5
b111 *
b111 +
b111 C
#1760
00
0-
07
0,
0!
02
03
04
08
09
0:
16
b0 /
b0 5
0.
b0 *
b0 +
0)
1(
b1 A
b0 B
b0 C
#1770
1,
06
10
17
12
13
18
19
b1 /
b1 5
b1 *
b1 +
b1 C
#1780
0!
16
1,
00
0-
07
02
03
14
08
09
1:
b10 /
b10 5
b10 *
b10 +
b10 C
#1790
1!
0,
1-
06
10
17
12
13
18
19
b11 /
b11 5
b11 *
b11 +
b11 C
#1800
16
0,
00
0-
07
0!
02
03
04
08
09
0:
b0 /
b0 5
1.
b100 *
b100 +
b100 C
#1810
1!
1,
06
10
17
12
13
18
19
b1 /
b1 5
b101 *
b101 +
b101 C
#1820
1!
16
1,
00
0-
07
02
03
14
08
09
1:
b10 /
b10 5
b110 *
b110 +
b110 C
#1830
0!
0,
1-
06
10
17
12
13
18
19
b11 /
b11 5
b111 *
b111 +
b111 C
#1840
0,
00
0-
07
0!
02
03
04
08
09
0:
16
b0 /
b0 5
0.
b0 *
b0 +
1)
b1 B
b0 C
#1850
1,
10
17
12
13
18
19
b1 /
b1 5
b1 *
b1 +
b1 C
#1860
0!
1,
00
0-
07
16
02
03
14
08
09
1:
b10 /
b10 5
b10 *
b10 +
b10 C
#1870
1!
1-
10
17
12
13
18
19
b11 /
b11 5
b11 *
b11 +
b11 C
#1880
0!
00
0-
07
16
0,
02
03
04
08
09
0:
b0 /
b0 5
1.
b100 *
b100 +
b100 C
#1890
1!
1,
10
17
12
13
18
19
b1 /
b1 5
b101 *
b101 +
b101 C
#1900
1!
1,
00
0-
07
16
02
03
14
08
09
1:
b10 /
b10 5
b110 *
b110 +
b110 C
#1910
1-
10
17
12
13
18
19
b11 /
b11 5
b111 *
b111 +
b111 C
#1920
00
0-
1,
0!
02
03
04
08
09
0:
06
17
b0 /
b0 5
0.
b0 *
b0 +
0)
0(
0'
1&
b1 ?
b0 @
b0 A
b0 B
b0 C
#1930
0,
07
10
12
13
18
19
b1 /
b1 5
b1 *
b1 +
b1 C
#1940
0!
17
00
0-
02
03
14
08
09
1:
b10 /
b10 5
b10 *
b10 +
b10 C
#1950
1!
1-
07
10
12
13
18
19
b11 /
b11 5
b11 *
b11 +
b11 C
#1960
1,
17
00
0-
1!
02
03
04
08
09
0:
b0 /
b0 5
1.
b100 *
b100 +
b100 C
#1970
0!
0,
07
10
12
13
18
19
b1 /
b1 5
b101 *
b101 +
b101 C
#1980
17
00
0-
02
03
14
08
09
1:
b10 /
b10 5
b110 *
b110 +
b110 C
#1990
1-
07
10
12
13
18
19
b11 /
b11 5
b111 *
b111 +
b111 C
#2000
1,
17
00
0-
0!
02
03
04
08
09
0:
06
b0 /
b0 5
0.
b0 *
b0 +
1)
b1 B
b0 C
#2010
0,
07
10
16
12
13
18
19
b1 /
b1 5
b1 *
b1 +
b1 C
#2020
0!
17
00
0-
06
0,
02
03
14
08
09
1:
b10 /
b10 5
b10 *
b10 +
b10 C
#2030
1!
1-
1,
07
10
16
12
13
18
19
b11 /
b11 5
b11 *
b11 +
b11 C
#2040
1!
17
00
0-
06
1,
02
03
04
08
09
0:
b0 /
b0 5
1.
b100 *
b100 +
b100 C
#2050
0!
0,
07
10
16
12
13
18
19
b1 /
b1 5
b101 *
b101 +
b101 C
#2060
0!
17
00
0-
06
0,
02
03
14
08
09
1:
b10 /
b10 5
b110 *
b110 +
b110 C
#2070
1!
1-
1,
07
10
16
12
13
18
19
b11 /
b11 5
b111 *
b111 +
b111 C
#2080
17
00
0-
1,
0!
02
03
04
08
09
0:
16
b0 /
b0 5
0.
b0 *
b0 +
0)
1(
b1 A
b0 B
b0 C
#2090
0,
07
06
10
12
13
18
19
b1 /
b1 5
b1 *
b1 +
b1 C
#2100
1,
0!
17
16
00
0-
02
03
14
08
09
1:
b10 /
b10 5
b10 *
b10 +
b10 C
#2110
1!
0,
1-
07
06
10
12
13
18
19
b11 /
b11 5
b11 *
b11 +
b11 C
#2120
1,
17
16
00
0-
1!
02
03
04
08
09
0:
b0 /
b0 5
1.
b100 *
b100 +
b100 C
#2130
0!
0,
07
06
10
12
13
18
19
b1 /
b1 5
b101 *
b101 +
b101 C
#2140
1!
1,
17
16
00
0-
02
03
14
08
09
1:
b10 /
b10 5
b110 *
b110 +
b110 C
#2150
0!
0,
1-
07
06
10
12
13
18
19
b11 /
b11 5
b111 *
b111 +
b111 C
#2160
1,
17
00
0-
0!
02
03
04
08
09
0:
16
b0 /
b0 5
0.
b0 *
b0 +
1)
b1 B
b0 C
#2170
0,
07
10
12
13
18
19
b1 /
b1 5
b1 *
b1 +
b1 C
#2180
0!
17
00
0-
16
1,
02
03
14
08
09
1:
b10 /
b10 5
b10 *
b10 +
b10 C
#2190
1!
1-
07
10
12
13
18
19
b11 /
b11 5
b11 *
b11 +
b11 C
#2200
1!
17
00
0-
16
1,
02
03
04
08
09
0:
b0 /
b0 5
1.
b100 *
b100 +
b100 C
#2210
0!
0,
07
10
12
13
18
19
b1 /
b1 5
b101 *
b101 +
b101 C
#2220
1!
17
00
0-
16
1,
02
03
14
08
09
1:
b10 /
b10 5
b110 *
b110 +
b110 C
#2230
1-
07
10
12
13
18
19
b11 /
b11 5
b111 *
b111 +
b111 C
#2240
00
0-
1,
0!
02
03
04
08
09
0:
06
17
b0 /
b0 5
0.
b0 *
b0 +
0)
0(
1'
b1 @
b0 A
b0 B
b0 C
#2250
10
12
13
18
19
b1 /
b1 5
b1 *
b1 +
b1 C
