Q6_Universal_Shift_Reg/q6_USR_design.v
`timescale 1ns/1ns

module mux_2x1(input A, input B, input S, output Y_2x1);
    assign Y_2x1 = ((~S) & A) | (S & B);
endmodule

// for 4x1 mux, A(00), B(01), C(10), D(11)
module mux_4x1(input A, input B, input C, input D, input [1:0] S, output Y_4x1);
    mux_2x1 mux_2x1_1(.A(A), .B(B), .S(S[0]), .Y_2x1(Y1));
    mux_2x1 mux_2x1_2(.A(C), .B(D), .S(S[0]), .Y_2x1(Y2));
    mux_2x1 mux_2x1_3(.A(Y1), .B(Y2), .S(S[1]), .Y_2x1(Y_4x1));
endmodule

module D_flipflop(input d, input clk, input reset, output reg q);
    always @(posedge clk or posedge reset)
    begin
        if (reset)
            q <= 1'b0;
        else
            q <= d;
    end
endmodule

/* 
    Universal shift register design
    I: input data
    S: shift control
    MSB_in: input data at MSB
    LSB_in: input data at LSB
    clk: clock
    clear: clear (active high)
    A: output data

    S  | Operation
    00 | No change
    01 | Shift right
    10 | Shift left
    11 | Parallel load
*/
module Universal_shift_reg(input [3:0] I, input [1:0] S, 
input MSB_in, input LSB_in, input clk, input clear, output [3:0] A);
    mux_4x1 mux_0(.A(A[0]), .B(A[1]), .C(LSB_in), .D(I[0]), .S(S), .Y_4x1(Y0));
    mux_4x1 mux_1(.A(A[1]), .B(A[2]), .C(A[0]), .D(I[1]), .S(S), .Y_4x1(Y1));
    mux_4x1 mux_2(.A(A[2]), .B(A[3]), .C(A[1]), .D(I[2]), .S(S), .Y_4x1(Y2));
    mux_4x1 mux_3(.A(A[3]), .B(MSB_in), .C(A[2]), .D(I[3]), .S(S), .Y_4x1(Y3));

    D_flipflop DFF0(.d(Y0), .clk(clk), .reset(clear), .q(A[0]));
    D_flipflop DFF1(.d(Y1), .clk(clk), .reset(clear), .q(A[1]));
    D_flipflop DFF2(.d(Y2), .clk(clk), .reset(clear), .q(A[2]));
    D_flipflop DFF3(.d(Y3), .clk(clk), .reset(clear), .q(A[3]));
endmodule

Q6_Universal_Shift_Reg/q6_USR_tb.v
`timescale 1ns/1ns
`include "q6_USR_design.v"

module Universal_shift_reg_test();
    reg [3:0] I;
    reg [1:0] S;
    reg clk, reset, MSB_in, LSB_in;
    wire [3:0] A;

    Universal_shift_reg uut(
        .I(I),
        .S(S),
        .MSB_in(MSB_in),
        .LSB_in(LSB_in),
        .clk(clk),
        .clear(reset),
        .A(A)
    );

    initial begin
        $dumpfile("q6_USR.vcd");
        $dumpvars(0, Universal_shift_reg_test);
        for (integer i = 0;i< 16;i = i+1)
        begin
            for (integer j = 0;j< 4;j = j+1)
            begin
                for (integer k = 0;k< 2;k = k+1)
                begin
                    for (integer l = 0;l< 2;l = l+1)
                    begin
                        I = i;
                        S = j;
                        MSB_in = k;
                        LSB_in = l;
                        clk = 0;
                        reset = 0;
                        #10;
                        clk = 1;
                        #10;
                    end
                end
            end
        end
        $finish;
    end

    initial begin
        $monitor("Time = %0t: I = %b, S = %b, MSB_in = %b, LSB_in = %b, clk = %b, A = %b", 
        $time, I, S, MSB_in, LSB_in, clk, A);
    end
endmodule

Q6_Universal_Shift_Reg/q6_USR.vcd
$date
	Fri Oct  4 22:16:01 2024
$end
$version
	Icarus Verilog
$end
$timescale
	1ns
$end
$scope module Universal_shift_reg_test $end
$var wire 4 ! A [3:0] $end
$var reg 4 " I [3:0] $end
$var reg 1 # LSB_in $end
$var reg 1 $ MSB_in $end
$var reg 2 % S [1:0] $end
$var reg 1 & clk $end
$var reg 1 ' reset $end
$scope module uut $end
$var wire 4 ( I [3:0] $end
$var wire 1 # LSB_in $end
$var wire 1 $ MSB_in $end
$var wire 2 ) S [1:0] $end
$var wire 1 ' clear $end
$var wire 1 & clk $end
$var wire 1 * Y3 $end
$var wire 1 + Y2 $end
$var wire 1 , Y1 $end
$var wire 1 - Y0 $end
$var wire 4 . A [3:0] $end
$scope module DFF0 $end
$var wire 1 & clk $end
$var wire 1 ' reset $end
$var wire 1 - d $end
$var reg 1 / q $end
$upscope $end
$scope module DFF1 $end
$var wire 1 & clk $end
$var wire 1 ' reset $end
$var wire 1 , d $end
$var reg 1 0 q $end
$upscope $end
$scope module DFF2 $end
$var wire 1 & clk $end
$var wire 1 ' reset $end
$var wire 1 + d $end
$var reg 1 1 q $end
$upscope $end
$scope module DFF3 $end
$var wire 1 & clk $end
$var wire 1 ' reset $end
$var wire 1 * d $end
$var reg 1 2 q $end
$upscope $end
$scope module mux_0 $end
$var wire 1 3 A $end
$var wire 1 4 B $end
$var wire 1 # C $end
$var wire 1 5 D $end
$var wire 2 6 S [1:0] $end
$var wire 1 - Y_4x1 $end
$var wire 1 7 Y2 $end
$var wire 1 8 Y1 $end
$scope module mux_2x1_1 $end
$var wire 1 3 A $end
$var wire 1 4 B $end
$var wire 1 9 S $end
$var wire 1 8 Y_2x1 $end
$upscope $end
$scope module mux_2x1_2 $end
$var wire 1 # A $end
$var wire 1 5 B $end
$var wire 1 : S $end
$var wire 1 7 Y_2x1 $end
$upscope $end
$scope module mux_2x1_3 $end
$var wire 1 8 A $end
$var wire 1 7 B $end
$var wire 1 ; S $end
$var wire 1 - Y_2x1 $end
$upscope $end
$upscope $end
$scope module mux_1 $end
$var wire 1 < A $end
$var wire 1 = B $end
$var wire 1 > C $end
$var wire 1 ? D $end
$var wire 2 @ S [1:0] $end
$var wire 1 , Y_4x1 $end
$var wire 1 A Y2 $end
$var wire 1 B Y1 $end
$scope module mux_2x1_1 $end
$var wire 1 < A $end
$var wire 1 = B $end
$var wire 1 C S $end
$var wire 1 B Y_2x1 $end
$upscope $end
$scope module mux_2x1_2 $end
$var wire 1 > A $end
$var wire 1 ? B $end
$var wire 1 D S $end
$var wire 1 A Y_2x1 $end
$upscope $end
$scope module mux_2x1_3 $end
$var wire 1 B A $end
$var wire 1 A B $end
$var wire 1 E S $end
$var wire 1 , Y_2x1 $end
$upscope $end
$upscope $end
$scope module mux_2 $end
$var wire 1 F A $end
$var wire 1 G B $end
$var wire 1 H C $end
$var wire 1 I D $end
$var wire 2 J S [1:0] $end
$var wire 1 + Y_4x1 $end
$var wire 1 K Y2 $end
$var wire 1 L Y1 $end
$scope module mux_2x1_1 $end
$var wire 1 F A $end
$var wire 1 G B $end
$var wire 1 M S $end
$var wire 1 L Y_2x1 $end
$upscope $end
$scope module mux_2x1_2 $end
$var wire 1 H A $end
$var wire 1 I B $end
$var wire 1 N S $end
$var wire 1 K Y_2x1 $end
$upscope $end
$scope module mux_2x1_3 $end
$var wire 1 L A $end
$var wire 1 K B $end
$var wire 1 O S $end
$var wire 1 + Y_2x1 $end
$upscope $end
$upscope $end
$scope module mux_3 $end
$var wire 1 P A $end
$var wire 1 $ B $end
$var wire 1 Q C $end
$var wire 1 R D $end
$var wire 2 S S [1:0] $end
$var wire 1 * Y_4x1 $end
$var wire 1 T Y2 $end
$var wire 1 U Y1 $end
$scope module mux_2x1_1 $end
$var wire 1 P A $end
$var wire 1 $ B $end
$var wire 1 V S $end
$var wire 1 U Y_2x1 $end
$upscope $end
$scope module mux_2x1_2 $end
$var wire 1 Q A $end
$var wire 1 R B $end
$var wire 1 W S $end
$var wire 1 T Y_2x1 $end
$upscope $end
$scope module mux_2x1_3 $end
$var wire 1 U A $end
$var wire 1 T B $end
$var wire 1 X S $end
$var wire 1 * Y_2x1 $end
$upscope $end
$upscope $end
$upscope $end
$scope begin $ivl_for_loop0 $end
$var integer 32 Y i [31:0] $end
$scope begin $ivl_for_loop1 $end
$var integer 32 Z j [31:0] $end
$scope begin $ivl_for_loop2 $end
$var integer 32 [ k [31:0] $end
$scope begin $ivl_for_loop3 $end
$var integer 32 \ l [31:0] $end
$upscope $end
$upscope $end
$upscope $end
$upscope $end
$upscope $end
$enddefinitions $end
#0
$dumpvars
b0 \
b0 [
b0 Z
b0 Y
0X
0W
0V
xU
xT
b0 S
0R
xQ
xP
0O
0N
0M
xL
xK
b0 J
0I
xH
xG
xF
0E
0D
0C
xB
xA
b0 @
0?
x>
x=
x<
0;
0:
09
x8
07
b0 6
05
x4
x3
x2
x1
x0
x/
bx .
x-
x,
x+
x*
b0 )
b0 (
0'
0&
b0 %
0$
0#
b0 "
bx !
$end
#10
1&
#20
17
0&
1#
b1 \
#30
1&
#40
07
0&
0#
1$
b1 [
b0 \
#50
1&
#60
17
0&
1#
b1 \
#70
1&
#80
0*
0A
0K
0U
0T
07
19
1:
1C
1D
1M
1N
1V
1W
0&
0#
0$
b1 %
b1 )
b1 6
b1 @
b1 J
b1 S
b1 Z
b0 [
b0 \
#90
0+
0L
0P
0G
b0xxx !
b0xxx .
02
1&
#100
0&
1#
b1 \
#110
0,
0B
0Q
0F
0=
b0xx !
b0xx .
01
1&
#120
1*
1U
0&
0#
1$
b1 [
b0 \
#130
0-
1+
08
1L
0H
0<
04
1P
1G
00
b100x !
b100x .
12
1&
#140
0&
1#
b1 \
#150
1,
1B
1Q
1F
1=
0>
03
11
b1100 !
b1100 .
0/
1&
#160
0,
0+
1T
1*
0B
1L
1U
09
0:
1;
0C
0D
1E
0M
0N
1O
0V
0W
1X
0&
0#
0$
b10 %
b10 )
b10 6
b10 @
b10 J
b10 S
b10 Z
b0 [
b0 \
#170
0*
0T
0L
0Q
0F
0=
b1000 !
b1000 .
01
1&
#180
1-
17
0&
1#
b1 \
#190
1,
0U
1A
18
0P
0G
1>
13
02
b1 !
b1 .
1/
1&
#200
0-
07
0&
0#
1$
b1 [
b0 \
#210
0,
1+
0A
08
1K
1B
0>
03
1H
1<
14
0/
b10 !
b10 .
10
1&
#220
1-
17
0&
1#
b1 \
#230
1*
0+
1,
1T
1L
0K
0B
1A
18
1Q
1F
1=
0H
0<
04
1>
13
11
00
b101 !
b101 .
1/
1&
#240
0,
0*
0-
08
0A
0L
0T
1B
07
19
1:
1C
1D
1M
1N
1V
1W
0&
0#
0$
b11 %
b11 )
b11 6
b11 @
b11 J
b11 S
b11 Z
b0 [
b0 \
#250
0B
0>
03
0Q
0F
0=
0/
b0 !
b0 .
01
1&
#260
0&
1#
b1 \
#270
1&
#280
1U
0&
0#
1$
b1 [
b0 \
#290
1&
#300
0&
1#
b1 \
#310
1&
#320
0U
09
0:
0;
0C
0D
0E
0M
0N
0O
0V
0W
0X
15
0&
0#
0$
b0 %
b0 )
b0 6
b0 @
b0 J
b0 S
b1 "
b1 (
b1 Y
b0 Z
b0 [
b0 \
#330
1&
#340
17
0&
1#
b1 \
#350
1&
#360
07
0&
0#
1$
b1 [
b0 \
#370
1&
#380
17
0&
1#
b1 \
#390
1&
#400
19
1:
1C
1D
1M
1N
1V
1W
0&
0#
0$
b1 %
b1 )
b1 6
b1 @
b1 J
b1 S
b1 Z
b0 [
b0 \
#410
1&
#420
0&
1#
b1 \
#430
1&
#440
1*
1U
0&
0#
1$
b1 [
b0 \
#450
1+
1L
1P
1G
b1000 !
b1000 .
12
1&
#460
0&
1#
b1 \
#470
1,
1B
1Q
1F
1=
b1100 !
b1100 .
11
1&
#480
0,
0+
1T
1*
07
0-
0B
1L
1U
09
0:
1;
0C
0D
1E
0M
0N
1O
0V
0W
1X
0&
0#
0$
b10 %
b10 )
b10 6
b10 @
b10 J
b10 S
b10 Z
b0 [
b0 \
#490
0*
0T
0L
0Q
0F
0=
b1000 !
b1000 .
01
1&
#500
1-
17
0&
1#
b1 \
#510
1,
0U
1A
18
0P
0G
1>
13
02
b1 !
b1 .
1/
1&
#520
0-
07
0&
0#
1$
b1 [
b0 \
#530
0,
1+
0A
08
1K
1B
0>
03
1H
1<
14
0/
b10 !
b10 .
10
1&
#540
1-
17
0&
1#
b1 \
#550
1*
0+
1,
1T
1L
0K
0B
1A
18
1Q
1F
1=
0H
0<
04
1>
13
11
00
b101 !
b101 .
1/
1&
#560
0,
0*
08
0A
0L
0T
1B
19
1:
1C
1D
1M
1N
1V
1W
0&
0#
0$
b11 %
b11 )
b11 6
b11 @
b11 J
b11 S
b11 Z
b0 [
b0 \
#570
0B
0Q
0F
0=
b1 !
b1 .
01
1&
#580
0&
1#
b1 \
#590
1&
#600
1U
0&
0#
1$
b1 [
b0 \
#610
1&
#620
0&
1#
b1 \
#630
1&
#640
18
1A
1-
07
0U
09
0:
0;
0C
0D
0E
0M
0N
0O
0V
0W
0X
05
1?
0&
0#
0$
b0 %
b0 )
b0 6
b0 @
b0 J
b0 S
b10 "
b10 (
b10 Y
b0 Z
b0 [
b0 \
#650
1&
#660
17
0&
1#
b1 \
#670
1&
#680
07
0&
0#
1$
b1 [
b0 \
#690
1&
#700
17
0&
1#
b1 \
#710
1&
#720
0-
08
07
19
1:
1C
1D
1M
1N
1V
1W
0&
0#
0$
b1 %
b1 )
b1 6
b1 @
b1 J
b1 S
b1 Z
b0 [
b0 \
#730
0>
03
b0 !
b0 .
0/
1&
#740
0&
1#
b1 \
#750
1&
#760
1*
1U
0&
0#
1$
b1 [
b0 \
#770
1+
1L
1P
1G
b1000 !
b1000 .
12
1&
#780
0&
1#
b1 \
#790
1,
1B
1Q
1F
1=
b1100 !
b1100 .
11
1&
#800
0,
0+
1T
1*
0B
0A
1L
1U
09
0:
1;
0C
0D
1E
0M
0N
1O
0V
0W
1X
0&
0#
0$
b10 %
b10 )
b10 6
b10 @
b10 J
b10 S
b10 Z
b0 [
b0 \
#810
0*
0T
0L
0Q
0F
0=
b1000 !
b1000 .
01
1&
#820
1-
17
0&
1#
b1 \
#830
1,
0U
1A
18
0P
0G
1>
13
02
b1 !
b1 .
1/
1&
#840
0-
07
0&
0#
1$
b1 [
b0 \
#850
0,
1+
0A
08
1K
1B
0>
03
1H
1<
14
0/
b10 !
b10 .
10
1&
#860
1-
17
0&
1#
b1 \
#870
1*
0+
1,
1T
1L
0K
0B
1A
18
1Q
1F
1=
0H
0<
04
1>
13
11
00
b101 !
b101 .
1/
1&
#880
0*
0-
08
0L
0T
1B
07
19
1:
1C
1D
1M
1N
1V
1W
0&
0#
0$
b11 %
b11 )
b11 6
b11 @
b11 J
b11 S
b11 Z
b0 [
b0 \
#890
18
0B
0>
03
1H
1<
14
0Q
0F
0=
0/
10
b10 !
b10 .
01
1&
#900
0&
1#
b1 \
#910
1&
#920
1U
0&
0#
1$
b1 [
b0 \
#930
1&
#940
0&
1#
b1 \
#950
1&
#960
0-
1B
1K
08
0A
1,
0U
09
0:
0;
0C
0D
0E
0M
0N
0O
0V
0W
0X
15
0&
0#
0$
b0 %
b0 )
b0 6
b0 @
b0 J
b0 S
b11 "
b11 (
b11 Y
b0 Z
b0 [
b0 \
#970
1&
#980
17
0&
1#
b1 \
#990
1&
#1000
07
0&
0#
1$
b1 [
b0 \
#1010
1&
#1020
17
0&
1#
b1 \
#1030
1&
#1040
0,
1-
0B
0K
18
1A
19
1:
1C
1D
1M
1N
1V
1W
0&
0#
0$
b1 %
b1 )
b1 6
b1 @
b1 J
b1 S
b1 Z
b0 [
b0 \
#1050
0-
08
1>
13
0H
0<
04
1/
b1 !
b1 .
00
1&
#1060
0&
1#
b1 \
#1070
0>
03
b0 !
b0 .
0/
1&
#1080
1*
1U
0&
0#
1$
b1 [
b0 \
#1090
1+
1L
1P
1G
b1000 !
b1000 .
12
1&
#1100
0&
1#
b1 \
#1110
1,
1B
1Q
1F
1=
b1100 !
b1100 .
11
1&
#1120
0,
0+
1T
1*
07
0-
0B
0A
1L
1U
09
0:
1;
0C
0D
1E
0M
0N
1O
0V
0W
1X
0&
0#
0$
b10 %
b10 )
b10 6
b10 @
b10 J
b10 S
b10 Z
b0 [
b0 \
#1130
0*
0T
0L
0Q
0F
0=
b1000 !
b1000 .
01
1&
#1140
1-
17
0&
1#
b1 \
#1150
1,
0U
1A
18
0P
0G
1>
13
02
b1 !
b1 .
1/
1&
#1160
0-
07
0&
0#
1$
b1 [
b0 \
#1170
0,
1+
0A
08
1K
1B
0>
03
1H
1<
14
0/
b10 !
b10 .
10
1&
#1180
1-
17
0&
1#
b1 \
#1190
1*
0+
1,
1T
1L
0K
0B
1A
18
1Q
1F
1=
0H
0<
04
1>
13
11
00
b101 !
b101 .
1/
1&
#1200
0*
08
0L
0T
1B
19
1:
1C
1D
1M
1N
1V
1W
0&
0#
0$
b11 %
b11 )
b11 6
b11 @
b11 J
b11 S
b11 Z
b0 [
b0 \
#1210
18
0B
1H
1<
14
0Q
0F
0=
10
b11 !
b11 .
01
1&
#1220
0&
1#
b1 \
#1230
1&
#1240
1U
0&
0#
1$
b1 [
b0 \
#1250
1&
#1260
0&
1#
b1 \
#1270
1&
#1280
1B
1K
18
1-
1,
07
1A
0U
09
0:
0;
0C
0D
0E
0M
0N
0O
0V
0W
0X
05
0?
1I
0&
0#
0$
b0 %
b0 )
b0 6
b0 @
b0 J
b0 S
b100 "
b100 (
b100 Y
b0 Z
b0 [
b0 \
#1290
1&
#1300
17
0&
1#
b1 \
#1310
1&
#1320
07
0&
0#
1$
b1 [
b0 \
#1330
1&
#1340
17
0&
1#
b1 \
#1350
1&
#1360
0,
0B
0A
07
19
1:
1C
1D
1M
1N
1V
1W
0&
0#
0$
b1 %
b1 )
b1 6
b1 @
b1 J
b1 S
b1 Z
b0 [
b0 \
#1370
0-
08
0H
0<
04
b1 !
b1 .
00
1&
#1380
0&
1#
b1 \
#1390
0>
03
b0 !
b0 .
0/
1&
#1400
1*
1U
0&
0#
1$
b1 [
b0 \
#1410
1+
1L
1P
1G
b1000 !
b1000 .
12
1&
#1420
0&
1#
b1 \
#1430
1,
1B
1Q
1F
1=
b1100 !
b1100 .
11
1&
#1440
0+
0,
1T
1*
0B
1L
0K
1U
09
0:
1;
0C
0D
1E
0M
0N
1O
0V
0W
1X
0&
0#
0$
b10 %
b10 )
b10 6
b10 @
b10 J
b10 S
b10 Z
b0 [
b0 \
#1450
0*
0T
0L
0Q
0F
0=
b1000 !
b1000 .
01
1&
#1460
1-
17
0&
1#
b1 \
#1470
1,
0U
1A
18
0P
0G
1>
13
02
b1 !
b1 .
1/
1&
#1480
0-
07
0&
0#
1$
b1 [
b0 \
#1490
0,
1+
0A
08
1K
1B
0>
03
1H
1<
14
0/
b10 !
b10 .
10
1&
#1500
1-
17
0&
1#
b1 \
#1510
1*
0+
1,
1T
1L
0K
0B
1A
18
1Q
1F
1=
0H
0<
04
1>
13
11
00
b101 !
b101 .
1/
1&
#1520
0,
0*
1+
0-
08
0A
0L
0T
1B
1K
07
19
1:
1C
1D
1M
1N
1V
1W
0&
0#
0$
b11 %
b11 )
b11 6
b11 @
b11 J
b11 S
b11 Z
b0 [
b0 \
#1530
0>
03
b100 !
b100 .
0/
1&
#1540
0&
1#
b1 \
#1550
1&
#1560
1U
0&
0#
1$
b1 [
b0 \
#1570
1&
#1580
0&
1#
b1 \
#1590
1&
#1600
0,
1L
1T
0B
0K
1+
0U
09
0:
0;
0C
0D
0E
0M
0N
0O
0V
0W
0X
15
0&
0#
0$
b0 %
b0 )
b0 6
b0 @
b0 J
b0 S
b101 "
b101 (
b101 Y
b0 Z
b0 [
b0 \
#1610
1&
#1620
17
0&
1#
b1 \
#1630
1&
#1640
07
0&
0#
1$
b1 [
b0 \
#1650
1&
#1660
17
0&
1#
b1 \
#1670
1&
#1680
0+
1,
0L
0T
1B
1K
19
1:
1C
1D
1M
1N
1V
1W
0&
0#
0$
b1 %
b1 )
b1 6
b1 @
b1 J
b1 S
b1 Z
b0 [
b0 \
#1690
1-
0,
18
0B
1H
1<
14
0Q
0F
0=
10
b10 !
b10 .
01
1&
#1700
0&
1#
b1 \
#1710
0-
08
0H
0<
04
1>
13
00
b1 !
b1 .
1/
1&
#1720
1*
1U
0&
0#
1$
b1 [
b0 \
#1730
1+
1L
0>
03
1P
1G
0/
b1000 !
b1000 .
12
1&
#1740
0&
1#
b1 \
#1750
1,
1B
1Q
1F
1=
b1100 !
b1100 .
11
1&
#1760
0+
0,
1T
1*
07
0-
0B
1L
0K
1U
09
0:
1;
0C
0D
1E
0M
0N
1O
0V
0W
1X
0&
0#
0$
b10 %
b10 )
b10 6
b10 @
b10 J
b10 S
b10 Z
b0 [
b0 \
#1770
0*
0T
0L
0Q
0F
0=
b1000 !
b1000 .
01
1&
#1780
1-
17
0&
1#
b1 \
#1790
1,
0U
1A
18
0P
0G
1>
13
02
b1 !
b1 .
1/
1&
#1800
0-
07
0&
0#
1$
b1 [
b0 \
#1810
0,
1+
0A
08
1K
1B
0>
03
1H
1<
14
0/
b10 !
b10 .
10
1&
#1820
1-
17
0&
1#
b1 \
#1830
1*
0+
1,
1T
1L
0K
0B
1A
18
1Q
1F
1=
0H
0<
04
1>
13
11
00
b101 !
b101 .
1/
1&
#1840
0,
0*
1+
08
0A
0L
0T
1B
1K
19
1:
1C
1D
1M
1N
1V
1W
0&
0#
0$
b11 %
b11 )
b11 6
b11 @
b11 J
b11 S
b11 Z
b0 [
b0 \
#1850
1&
#1860
0&
1#
b1 \
#1870
1&
#1880
1U
0&
0#
1$
b1 [
b0 \
#1890
1&
#1900
0&
1#
b1 \
#1910
1&
#1920
18
1A
0,
1L
1T
1-
0B
0K
1+
07
0U
09
0:
0;
0C
0D
0E
0M
0N
0O
0V
0W
0X
05
1?
0&
0#
0$
b0 %
b0 )
b0 6
b0 @
b0 J
b0 S
b110 "
b110 (
b110 Y
b0 Z
b0 [
b0 \
#1930
1&
#1940
17
0&
1#
b1 \
#1950
1&
#1960
07
0&
0#
1$
b1 [
b0 \
#1970
1&
#1980
17
0&
1#
b1 \
#1990
1&
#2000
0-
0+
1,
08
0L
0T
1B
1K
07
19
1:
1C
1D
1M
1N
1V
1W
0&
0#
0$
b1 %
b1 )
b1 6
b1 @
b1 J
b1 S
b1 Z
b0 [
b0 \
#2010
1-
0,
18
0B
0>
03
1H
1<
14
0Q
0F
0=
0/
10
b10 !
b10 .
01
1&
#2020
0&
1#
b1 \
#2030
0-
08
0H
0<
04
1>
13
00
b1 !
b1 .
1/
1&
#2040
1*
1U
0&
0#
1$
b1 [
b0 \
#2050
1+
1L
0>
03
1P
1G
0/
b1000 !
b1000 .
12
1&
#2060
0&
1#
b1 \
#2070
1,
1B
1Q
1F
1=
b1100 !
b1100 .
11
1&
#2080
0,
0+
1T
1*
0B
0A
1L
0K
1U
09
0:
1;
0C
0D
1E
0M
0N
1O
0V
0W
1X
0&
0#
0$
b10 %
b10 )
b10 6
b10 @
b10 J
b10 S
b10 Z
b0 [
b0 \
#2090
0*
0T
0L
0Q
0F
0=
b1000 !
b1000 .
01
1&
#2100
1-
17
0&
1#
b1 \
#2110
1,
0U
1A
18
0P
0G
1>
13
02
b1 !
b1 .
1/
1&
#2120
0-
07
0&
0#
1$
b1 [
b0 \
#2130
0,
1+
0A
08
1K
1B
0>
03
1H
1<
14
0/
b10 !
b10 .
10
1&
#2140
1-
17
0&
1#
b1 \
#2150
1*
0+
1,
1T
1L
0K
0B
1A
18
1Q
1F
1=
0H
0<
04
1>
13
11
00
b101 !
b101 .
1/
1&
#2160
0*
1+
0-
08
0L
0T
1B
1K
07
19
1:
1C
1D
1M
1N
1V
1W
0&
0#
0$
b11 %
b11 )
b11 6
b11 @
b11 J
b11 S
b11 Z
b0 [
b0 \
#2170
18
0>
03
1H
1<
14
0/
b110 !
b110 .
10
1&
#2180
0&
1#
b1 \
#2190
1&
#2200
1U
0&
0#
1$
b1 [
b0 \
#2210
1&
#2220
0&
1#
b1 \
#2230
1&
#2240
0-
1L
1T
08
1B
0A
1,
1K
1+
0U
09
0:
0;
0C
0D
0E
0M
0N
0O
0V
0W
0X
15
0&
0#
0$
b0 %
b0 )
b0 6
b0 @
b0 J
b0 S
b111 "
b111 (
b111 Y
b0 Z
b0 [
b0 \
#2250
1&
#2260
17
0&
1#
b1 \
#2270
1&
#2280
07
0&
0#
1$
b1 [
b0 \
#2290
1&
#2300
17
0&
1#
b1 \
#2310
1&
#2320
0+
1-
0L
0T
18
1A
19
1:
1C
1D
1M
1N
1V
1W
0&
0#
0$
b1 %
b1 )
b1 6
b1 @
b1 J
b1 S
b1 Z
b0 [
b0 \
#2330
0,
0B
1>
13
0Q
0F
0=
1/
b11 !
b11 .
01
1&
#2340
0&
1#
b1 \
#2350
0-
08
0H
0<
04
b1 !
b1 .
00
1&
#2360
1*
1U
0&
0#
1$
b1 [
b0 \
#2370
1+
1L
0>
03
1P
1G
0/
b1000 !
b1000 .
12
1&
#2380
0&
1#
b1 \
#2390
1,
1B
1Q
1F
1=
b1100 !
b1100 .
11
1&
#2400
0,
0+
1T
1*
07
0-
0B
0A
1L
0K
1U
09
0:
1;
0C
0D
1E
0M
0N
1O
0V
0W
1X
0&
0#
0$
b10 %
b10 )
b10 6
b10 @
b10 J
b10 S
b10 Z
b0 [
b0 \
#2410
0*
0T
0L
0Q
0F
0=
b1000 !
b1000 .
01
1&
#2420
1-
17
0&
1#
b1 \
#2430
1,
0U
1A
18
0P
0G
1>
13
02
b1 !
b1 .
1/
1&
#2440
0-
07
0&
0#
1$
b1 [
b0 \
#2450
0,
1+
0A
08
1K
1B
0>
03
1H
1<
14
0/
b10 !
b10 .
10
1&
#2460
1-
17
0&
1#
b1 \
#2470
1*
0+
1,
1T
1L
0K
0B
1A
18
1Q
1F
1=
0H
0<
04
1>
13
11
00
b101 !
b101 .
1/
1&
#2480
0*
1+
08
0L
0T
1B
1K
19
1:
1C
1D
1M
1N
1V
1W
0&
0#
0$
b11 %
b11 )
b11 6
b11 @
b11 J
b11 S
b11 Z
b0 [
b0 \
#2490
18
1H
1<
14
b111 !
b111 .
10
1&
#2500
0&
1#
b1 \
#2510
1&
#2520
1U
0&
0#
1$
b1 [
b0 \
#2530
1&
#2540
0&
1#
b1 \
#2550
1&
#2560
1L
1T
18
1-
1B
1,
1+
07
1A
1K
0U
09
0:
0;
0C
0D
0E
0M
0N
0O
0V
0W
0X
05
0?
0I
1R
0&
0#
0$
b0 %
b0 )
b0 6
b0 @
b0 J
b0 S
b1000 "
b1000 (
b1000 Y
b0 Z
b0 [
b0 \
#2570
1&
#2580
17
0&
1#
b1 \
#2590
1&
#2600
07
0&
0#
1$
b1 [
b0 \
#2610
1&
#2620
17
0&
1#
b1 \
#2630
1&
#2640
0+
0A
0L
0K
07
19
1:
1C
1D
1M
1N
1V
1W
0&
0#
0$
b1 %
b1 )
b1 6
b1 @
b1 J
b1 S
b1 Z
b0 [
b0 \
#2650
0,
0B
0Q
0F
0=
b11 !
b11 .
01
1&
#2660
0&
1#
b1 \
#2670
0-
08
0H
0<
04
b1 !
b1 .
00
1&
#2680
1*
1U
0&
0#
1$
b1 [
b0 \
#2690
1+
1L
0>
03
1P
1G
0/
b1000 !
b1000 .
12
1&
#2700
0&
1#
b1 \
#2710
1,
1B
1Q
1F
1=
b1100 !
b1100 .
11
1&
#2720
1*
0,
0+
0B
1L
1T
1U
09
0:
1;
0C
0D
1E
0M
0N
1O
0V
0W
1X
0&
0#
0$
b10 %
b10 )
b10 6
b10 @
b10 J
b10 S
b10 Z
b0 [
b0 \
#2730
0*
0T
0L
0Q
0F
0=
b1000 !
b1000 .
01
1&
#2740
1-
17
0&
1#
b1 \
#2750
1,
0U
1A
18
0P
0G
1>
13
02
b1 !
b1 .
1/
1&
#2760
0-
07
0&
0#
1$
b1 [
b0 \
#2770
0,
1+
0A
08
1K
1B
0>
03
1H
1<
14
0/
b10 !
b10 .
10
1&
#2780
1-
17
0&
1#
b1 \
#2790
1*
0+
1,
1T
1L
0K
0B
1A
18
1Q
1F
1=
0H
0<
04
1>
13
11
00
b101 !
b101 .
1/
1&
#2800
0,
0-
08
0A
0L
1B
07
19
1:
1C
1D
1M
1N
1V
1W
0&
0#
0$
b11 %
b11 )
b11 6
b11 @
b11 J
b11 S
b11 Z
b0 [
b0 \
#2810
0B
1L
0>
03
0Q
0F
0=
1P
1G
0/
01
b1000 !
b1000 .
12
1&
#2820
0&
1#
b1 \
#2830
1&
#2840
1U
0&
0#
1$
b1 [
b0 \
#2850
1&
#2860
0&
1#
b1 \
#2870
1&
#2880
0+
0L
0T
1*
1U
09
0:
0;
0C
0D
0E
0M
0N
0O
0V
0W
0X
15
0&
0#
0$
b0 %
b0 )
b0 6
b0 @
b0 J
b0 S
b1001 "
b1001 (
b1001 Y
b0 Z
b0 [
b0 \
#2890
1&
#2900
17
0&
1#
b1 \
#2910
1&
#2920
07
0&
0#
1$
b1 [
b0 \
#2930
1&
#2940
17
0&
1#
b1 \
#2950
1&
#2960
0*
1+
0U
1L
1T
19
1:
1C
1D
1M
1N
1V
1W
0&
0#
0$
b1 %
b1 )
b1 6
b1 @
b1 J
b1 S
b1 Z
b0 [
b0 \
#2970
1,
0+
1B
0L
1Q
1F
1=
0P
0G
11
b100 !
b100 .
02
1&
#2980
0&
1#
b1 \
#2990
0,
1-
0B
18
0Q
0F
0=
1H
1<
14
01
b10 !
b10 .
10
1&
#3000
1*
1U
0&
0#
1$
b1 [
b0 \
#3010
0-
1+
08
1L
1>
13
0H
0<
04
1P
1G
1/
00
b1001 !
b1001 .
12
1&
#3020
0&
1#
b1 \
#3030
1,
1B
1Q
1F
1=
0>
03
11
b1100 !
b1100 .
0/
1&
#3040
1*
0,
0+
07
0-
0B
1L
1T
1U
09
0:
1;
0C
0D
1E
0M
0N
1O
0V
0W
1X
0&
0#
0$
b10 %
b10 )
b10 6
b10 @
b10 J
b10 S
b10 Z
b0 [
b0 \
#3050
0*
0T
0L
0Q
0F
0=
b1000 !
b1000 .
01
1&
#3060
1-
17
0&
1#
b1 \
#3070
1,
0U
1A
18
0P
0G
1>
13
02
b1 !
b1 .
1/
1&
#3080
0-
07
0&
0#
1$
b1 [
b0 \
#3090
0,
1+
0A
08
1K
1B
0>
03
1H
1<
14
0/
b10 !
b10 .
10
1&
#3100
1-
17
0&
1#
b1 \
