Q2_Combinational_Functions/q2_design.v
`timescale 1ns/1ns

module comb_ckt(input A, input B, input C, input D, input E, input F, 
output Y1, output Y2, output Y3, output Y4, output Y5, output temp);
    
    // int_x are the intermediate wires used for making connections between gates
    nand(int1, A, B);
    nand(int2, C, D);
    nand(Y1, int1, int2);

    nand(int3, A, B, C);
    nand(int5, int3, int3);
    nand(int4, D, E);
    nand(int6, int4, int4);
    nor(int7, int5, int6);
    nand(int8, F, F);
    nor(Y2, int7, int8);

    nand(int9, A, A);
    nand(int10, int9, B);
    nand(int11, C, D);
    nand(int12, E, E);
    nand(int13, int11, int12);
    nand(Y3, int10, int13);

    nand(int14, A, A);
    nand(int15, int14, D);
    nand(int16, B, D);
    nand(Y4, int15, int16);

    nand(notB, B, B);
    nand(notC, C, C);
    nand(notD, D, D);
    nand(int17, C, notD);
    nand(int18, notB, notD);
    nand(int19, A, B, notC, D);
    nand(Y5, int17, int18, int19);

    // Cross - verification
    // assign temp = ((A & B) | (C & D));
    // assign temp = ((A & B & C) | (D & E)) & F;
    // assign temp = ~( (A | (~B)) & ((C & D) | E) );
    // assign temp = ((~A) & D) | (B  & D);
    assign temp = (C & (~D)) | ((~B) & (~D)) | (A & B & (~C) & D);
endmodule

Q2_Combinational_Functions/q2_tb.v
`timescale 1ns/1ns

`include "q2_design.v"
module comb_ckt_test;
    reg A, B, C, D, E, F;

    comb_ckt uut(
        .A(A),
        .B(B),
        .C(C),
        .D(D),
        .E(E),
        .F(F),
        .Y1(Y1),
        .Y2(Y2),
        .Y3(Y3),
        .Y4(Y4),
        .Y5(Y5),
        .temp(temp)
    );

    initial begin
        $dumpfile("q2.vcd");
        $dumpvars(0, comb_ckt_test);

        for (integer i = 0;i< 2;i = i+1)
        begin
            for (integer j = 0;j< 2;j = j+1)
            begin
                for (integer k = 0;k< 2;k = k+1)
                begin
                    for (integer l = 0;l< 2;l = l+1)
                    begin
                        for (integer m = 0;m< 2;m = m+1)
                        begin
                            for (integer n = 0;n< 2;n = n+1)
                            begin
                                A = i; B = j; C = k; D = l; E = m; F = n;
                                #10;
                            end
                        end
                    end
                end                
            end
        end
        
        $finish;
    end

    initial begin
        $monitor("Time = %0t: A = %b, B = %b, C = %b, D = %b, E = %b, F = %b, Y5 = %b, temp = %b", 
        $time, A, B, C, D, E, F, Y5, temp);
    end
endmodule

Q2_Combinational_Functions/q2.vcd
$date
	Wed Oct  2 18:44:02 2024
$end
$version
	Icarus Verilog
$end
$timescale
	1ns
$end
$scope module comb_ckt_test $end
$var wire 1 ! temp $end
$var wire 1 " Y5 $end
$var wire 1 # Y4 $end
$var wire 1 $ Y3 $end
$var wire 1 % Y2 $end
$var wire 1 & Y1 $end
$var reg 1 ' A $end
$var reg 1 ( B $end
$var reg 1 ) C $end
$var reg 1 * D $end
$var reg 1 + E $end
$var reg 1 , F $end
$scope module uut $end
$var wire 1 ' A $end
$var wire 1 ( B $end
$var wire 1 ) C $end
$var wire 1 * D $end
$var wire 1 + E $end
$var wire 1 , F $end
$var wire 1 & Y1 $end
$var wire 1 % Y2 $end
$var wire 1 $ Y3 $end
$var wire 1 # Y4 $end
$var wire 1 " Y5 $end
$var wire 1 - int1 $end
$var wire 1 . int10 $end
$var wire 1 / int11 $end
$var wire 1 0 int12 $end
$var wire 1 1 int13 $end
$var wire 1 2 int14 $end
$var wire 1 3 int15 $end
$var wire 1 4 int16 $end
$var wire 1 5 int17 $end
$var wire 1 6 int18 $end
$var wire 1 7 int19 $end
$var wire 1 8 int2 $end
$var wire 1 9 int3 $end
$var wire 1 : int4 $end
$var wire 1 ; int5 $end
$var wire 1 < int6 $end
$var wire 1 = int7 $end
$var wire 1 > int8 $end
$var wire 1 ? int9 $end
$var wire 1 @ notB $end
$var wire 1 A notC $end
$var wire 1 B notD $end
$var wire 1 ! temp $end
$upscope $end
$scope begin $ivl_for_loop0 $end
$var integer 32 C i [31:0] $end
$scope begin $ivl_for_loop1 $end
$var integer 32 D j [31:0] $end
$scope begin $ivl_for_loop2 $end
$var integer 32 E k [31:0] $end
$scope begin $ivl_for_loop3 $end
$var integer 32 F l [31:0] $end
$scope begin $ivl_for_loop4 $end
$var integer 32 G m [31:0] $end
$scope begin $ivl_for_loop5 $end
$var integer 32 H n [31:0] $end
$upscope $end
$upscope $end
$upscope $end
$upscope $end
$upscope $end
$upscope $end
$upscope $end
$enddefinitions $end
#0
$dumpvars
b0 H
b0 G
b0 F
b0 E
b0 D
b0 C
1B
1A
1@
1?
1>
1=
0<
0;
1:
19
18
17
06
15
14
13
12
01
10
1/
1.
1-
0,
0+
0*
0)
0(
0'
0&
0%
1$
0#
1"
1!
$end
#10
0>
1,
b1 H
#20
0$
11
1>
00
0,
1+
b1 G
b0 H
#30
0>
1,
b1 H
#40
0!
1$
0"
01
1#
16
1>
10
03
0B
0,
0+
1*
b1 F
b0 G
b0 H
#50
0>
1,
b1 H
#60
0=
0$
1<
11
1>
0:
00
0,
1+
b1 G
b0 H
#70
1%
0>
1,
b1 H
#80
1!
1$
1=
1"
0%
01
0<
0#
05
06
1>
10
1:
13
1B
0A
0,
0+
0*
1)
b1 E
b0 F
b0 G
b0 H
#90
0>
1,
b1 H
#100
0$
11
1>
00
0,
1+
b1 G
b0 H
#110
0>
1,
b1 H
#120
0!
0"
1&
1#
15
16
1>
10
08
0/
03
0B
0,
0+
1*
b1 F
b0 G
b0 H
#130
0>
1,
b1 H
#140
0=
1<
1>
0:
00
0,
1+
b1 G
b0 H
#150
1%
0>
1,
b1 H
#160
1=
0%
0<
0#
0&
01
1$
1>
10
1:
13
1B
18
1/
1A
0.
0@
0,
0+
0*
0)
1(
b1 D
b0 E
b0 F
b0 G
b0 H
#170
0>
1,
b1 H
#180
11
1>
00
0,
1+
b1 G
b0 H
#190
0>
1,
b1 H
#200
01
1#
1>
10
03
04
0B
0,
0+
1*
b1 F
b0 G
b0 H
#210
0>
1,
b1 H
#220
0=
1<
11
1>
0:
00
0,
1+
b1 G
b0 H
#230
1%
0>
1,
b1 H
#240
1!
1=
1"
0%
01
0<
0#
05
1>
10
1:
13
14
1B
0A
0,
0+
0*
1)
b1 E
b0 F
b0 G
b0 H
#250
0>
1,
b1 H
#260
11
1>
00
0,
1+
b1 G
b0 H
#270
0>
1,
b1 H
#280
0!
0"
1&
1#
15
1>
10
08
0/
03
04
0B
0,
0+
1*
b1 F
b0 G
b0 H
#290
0>
1,
b1 H
#300
0=
1<
1>
0:
00
0,
1+
b1 G
b0 H
#310
1%
0>
1,
b1 H
#320
1!
1=
1"
0%
0<
0&
01
1$
0#
06
1>
10
1:
13
1B
18
1/
1A
1.
14
1@
0?
02
0,
0+
0*
0)
0(
1'
b1 C
b0 D
b0 E
b0 F
b0 G
b0 H
#330
0>
1,
b1 H
#340
0$
11
1>
00
0,
1+
b1 G
b0 H
#350
0>
1,
b1 H
#360
0!
1$
0"
01
16
1>
10
0B
0,
0+
1*
b1 F
b0 G
b0 H
#370
0>
1,
b1 H
#380
0=
0$
1<
11
1>
0:
00
0,
1+
b1 G
b0 H
#390
1%
0>
1,
b1 H
#400
1!
1$
1=
1"
0%
01
0<
05
06
1>
10
1:
1B
0A
0,
0+
0*
1)
b1 E
b0 F
b0 G
b0 H
#410
0>
1,
b1 H
#420
0$
11
1>
00
0,
1+
b1 G
b0 H
#430
0>
1,
b1 H
#440
0!
0"
1&
15
16
1>
10
08
0/
0B
0,
0+
1*
b1 F
b0 G
b0 H
#450
0>
1,
b1 H
#460
0=
1<
1>
0:
00
0,
1+
b1 G
b0 H
#470
1%
0>
1,
b1 H
#480
1=
1$
0%
0<
01
1>
10
1:
1B
18
1/
1A
0-
0@
0,
0+
0*
0)
1(
b1 D
b0 E
b0 F
b0 G
b0 H
#490
0>
1,
b1 H
#500
0$
11
1>
00
0,
1+
b1 G
b0 H
#510
0>
1,
b1 H
#520
1$
01
1#
1"
1!
1>
10
04
0B
07
0,
0+
1*
b1 F
b0 G
b0 H
#530
0>
1,
b1 H
#540
0=
0$
1<
11
1>
0:
00
0,
1+
b1 G
b0 H
#550
1%
0>
1,
b1 H
#560
1$
0%
01
0<
0#
05
1"
1!
1;
1>
10
1:
14
1B
17
09
0A
0,
0+
0*
1)
b1 E
b0 F
b0 G
b0 H
#570
1%
0>
1,
b1 H
#580
0$
0%
11
1>
00
0,
1+
b1 G
b0 H
#590
1%
0>
1,
b1 H
#600
0!
0"
0%
1#
15
1>
10
08
0/
04
0B
0,
0+
1*
b1 F
b0 G
b0 H
#610
1%
0>
1,
b1 H
#620
0%
1<
1>
0:
00
0,
1+
b1 G
b0 H
#630
1%
0>
1,
b1 H
#640
b10 C
b10 D
b10 E
b10 F
b10 G
b10 H
